multipliers16/traditional_multiplier16/msim/presynth/full_adder.v
`timescale 1ns / 1ps
//////////////////////////////////////////////////////////////////////////////////
// Company: 
// Engineer: 
// 
// Create Date:    15:11:39 06/09/2020 
// Design Name: 
// Module Name:    full_adder 
// Project Name: 
// Target Devices: 
// Tool versions: 
// Description: 
//
// Dependencies: 
//
// Revision: 
// Revision 0.01 - File Created
// Additional Comments: 
//
//////////////////////////////////////////////////////////////////////////////////
module full_adder(input1_i,input2_i,carry_i,sum_o,carry_o);
input input1_i, input2_i;
input carry_i;
output sum_o;
output carry_o;

assign sum_o = input1_i ^ input2_i ^ carry_i;
assign carry_o = (input1_i & input2_i) | (input1_i & carry_i) | (input2_i & carry_i);

endmodule

adders16/xnor_based_ripple_carry_adder16/msim/presynth/xnor_full_adder.v
`timescale 1ns / 1ps
//////////////////////////////////////////////////////////////////////////////////
// Company: 
// Engineer: 
// 
// Create Date:    15:11:39 06/09/2020 
// Design Name: 
// Module Name:    full_adder 
// Project Name: 
// Target Devices: 
// Tool versions: 
// Description: 
//
// Dependencies: 
//
// Revision: 
// Revision 0.01 - File Created
// Additional Comments: 
//
//////////////////////////////////////////////////////////////////////////////////
module xnor_full_adder(input1_i,input2_i,carry_i,sum_o,carry_o);
input input1_i, input2_i;
input carry_i;
output sum_o;
output carry_o;

assign sum_o = (~(input1_i ^ input2_i)) & carry_i;
assign carry_o = ((input1_i ^ input2_i) & carry_i) | (input1_i & input2_i);

endmodule

adders/xnor_based_carry_lookahead_adder16/snps/xnor_based_carry_lookahead_adder16.v
`timescale 1ns / 1ps
//////////////////////////////////////////////////////////////////////////////////
// Company: 
// Engineer: 
// 
// Create Date:    14:19:28 06/09/2020 
// Design Name: 
// Module Name:    ripple_carry_adder 
// Project Name: 
// Target Devices: 
// Tool versions: 
// Description: 
//
// Dependencies: 
//
// Revision: 
// Revision 0.01 - File Created
// Additional Comments: 
//
//////////////////////////////////////////////////////////////////////////////////
module xnor_based_carry_lookahead_adder16(add1_i,add2_i,result_o);
parameter width = 16;
parameter lower_width = 4;
input [width-1:0] add1_i;
input [width-1:0] add2_i;
output [width:0] result_o;

wire [width:0] carry_w;
wire [width-1:0] generate_w, propagate_w, sum_w;


genvar i;

generate
for(i=0; i<width; i = i+1)
begin 
  if(i < lower_width)
    begin
      xnor_full_adder xfa(.input1_i(add1_i[i]), .input2_i(add2_i[i]), .carry_i(carry_w[i]), .sum_o(sum_w[i]), .carry_o());
    end
  else
    begin   
      full_adder fa(.input1_i(add1_i[i]), .input2_i(add2_i[i]), .carry_i(carry_w[i]), .sum_o(sum_w[i]), .carry_o());  
    end
 end

endgenerate

genvar j;

generate
for(j=0; j<width; j = j+1)
begin
assign generate_w[j] = add1_i[j] & add2_i[j];
assign propagate_w[j] = add1_i[j] | add2_i[j];
assign carry_w[j+1] = generate_w[j]| (propagate_w[j] & carry_w[j]);
end

endgenerate

assign carry_w[0] = 1'b1;
assign result_o = {carry_w[width],sum_w};
endmodule

adders16/xnor_based_carry_lookahead_adder16/msim/presynth/xnor_based_carry_lookahead_adder16_tb.v
`timescale 1ns / 1ps
//////////////////////////////////////////////////////////////////////////////////
// Company: 
// Engineer: 
// 
// Create Date: 05/05/2020 01:15:36 AM
// Design Name: 
// Module Name: Test_Bench
// Project Name: 
// Target Devices: 
// Tool Versions: 
// Description: 
// 
// Dependencies: 
// 
// Revision:
// Revision 0.01 - File Created
// Additional Comments:
// 
//////////////////////////////////////////////////////////////////////////////////


module xnor_based_carry_lookahead_adder16_tb;
reg [15:0]add1_i;
reg [15:0]add2_i;
wire [16:0]result_o;


xnor_based_carry_lookahead_adder16 xcla(add1_i,add2_i,result_o);

initial begin
   $dumpfile("xnor_based_carry_lookahead_adder16_sim.vcd");
   $dumpvars(2,xnor_based_carry_lookahead_adder16_tb);

   
   add1_i = 16'h0000;
   add2_i = 16'h0000;
   #10
   add1_i = 16'h29AF;
   add2_i = 16'h7A1B;
   #10
   add1_i = 16'h1100;
   add2_i = 16'h1111;
   #10
   add1_i = 16'h8116;
   add2_i = 16'h1CCE;
   #5
   add1_i = 16'h4482;
   add2_i = 16'h3BCD;
   #2
   add1_i = 16'h8943;
   add2_i = 16'hFFFF;
   #10
   add1_i = 16'hABCD;
   add2_i = 16'h0000;
   #10
   add1_i = 16'h0000;
   add2_i = 16'h1234;
   #10
   add1_i = 16'h1111;
   add2_i = 16'hEEAA;
  #10
   add1_i = 16'h5555;
   add2_i = 16'hAAAA;
  #10
   add1_i = 16'h8051;
   add2_i = 16'h8086;
  #5
  add1_i = 16'hFADC;
  add2_i = 16'h00DC;
 #2
  add1_i = 16'h4096;
  add2_i = 16'h2048;
 #10
  add1_i = 16'h1024;
  add2_i = 16'h8192;
  #100
   add1_i = 16'h0000;
   add2_i = 16'h0001;
  #100
  
   $finish;
    
   
 end

initial begin

$monitor($time , " add1_i= %h, add2_i = %h, result_o = %h ",add1_i, add2_i, result_o);
end
	
	
	
endmodule

adders16/xnor_based_carry_lookahead_adder16/msim/presynth/xnor_based_carry_lookahead_adder16_sim.vcd
$date
	Thu Aug  6 20:25:48 2020
$end
$version
	ModelSim Version 6.6d
$end
$timescale
	1ps
$end
$scope module xnor_based_carry_lookahead_adder16_tb $end
$var reg 16 ! add1_i [15:0] $end
$var reg 16 " add2_i [15:0] $end
$var wire 1 # result_o [16] $end
$var wire 1 $ result_o [15] $end
$var wire 1 % result_o [14] $end
$var wire 1 & result_o [13] $end
$var wire 1 ' result_o [12] $end
$var wire 1 ( result_o [11] $end
$var wire 1 ) result_o [10] $end
$var wire 1 * result_o [9] $end
$var wire 1 + result_o [8] $end
$var wire 1 , result_o [7] $end
$var wire 1 - result_o [6] $end
$var wire 1 . result_o [5] $end
$var wire 1 / result_o [4] $end
$var wire 1 0 result_o [3] $end
$var wire 1 1 result_o [2] $end
$var wire 1 2 result_o [1] $end
$var wire 1 3 result_o [0] $end
$scope module xcla $end
$var parameter 32 4 width $end
$var parameter 32 5 lower_width $end
$var wire 1 6 add1_i [15] $end
$var wire 1 7 add1_i [14] $end
$var wire 1 8 add1_i [13] $end
$var wire 1 9 add1_i [12] $end
$var wire 1 : add1_i [11] $end
$var wire 1 ; add1_i [10] $end
$var wire 1 < add1_i [9] $end
$var wire 1 = add1_i [8] $end
$var wire 1 > add1_i [7] $end
$var wire 1 ? add1_i [6] $end
$var wire 1 @ add1_i [5] $end
$var wire 1 A add1_i [4] $end
$var wire 1 B add1_i [3] $end
$var wire 1 C add1_i [2] $end
$var wire 1 D add1_i [1] $end
$var wire 1 E add1_i [0] $end
$var wire 1 F add2_i [15] $end
$var wire 1 G add2_i [14] $end
$var wire 1 H add2_i [13] $end
$var wire 1 I add2_i [12] $end
$var wire 1 J add2_i [11] $end
$var wire 1 K add2_i [10] $end
$var wire 1 L add2_i [9] $end
$var wire 1 M add2_i [8] $end
$var wire 1 N add2_i [7] $end
$var wire 1 O add2_i [6] $end
$var wire 1 P add2_i [5] $end
$var wire 1 Q add2_i [4] $end
$var wire 1 R add2_i [3] $end
$var wire 1 S add2_i [2] $end
$var wire 1 T add2_i [1] $end
$var wire 1 U add2_i [0] $end
$var wire 1 # result_o [16] $end
$var wire 1 $ result_o [15] $end
$var wire 1 % result_o [14] $end
$var wire 1 & result_o [13] $end
$var wire 1 ' result_o [12] $end
$var wire 1 ( result_o [11] $end
$var wire 1 ) result_o [10] $end
$var wire 1 * result_o [9] $end
$var wire 1 + result_o [8] $end
$var wire 1 , result_o [7] $end
$var wire 1 - result_o [6] $end
$var wire 1 . result_o [5] $end
$var wire 1 / result_o [4] $end
$var wire 1 0 result_o [3] $end
$var wire 1 1 result_o [2] $end
$var wire 1 2 result_o [1] $end
$var wire 1 3 result_o [0] $end
$var wire 1 V carry_w [16] $end
$var wire 1 W carry_w [15] $end
$var wire 1 X carry_w [14] $end
$var wire 1 Y carry_w [13] $end
$var wire 1 Z carry_w [12] $end
$var wire 1 [ carry_w [11] $end
$var wire 1 \ carry_w [10] $end
$var wire 1 ] carry_w [9] $end
$var wire 1 ^ carry_w [8] $end
$var wire 1 _ carry_w [7] $end
$var wire 1 ` carry_w [6] $end
$var wire 1 a carry_w [5] $end
$var wire 1 b carry_w [4] $end
$var wire 1 c carry_w [3] $end
$var wire 1 d carry_w [2] $end
$var wire 1 e carry_w [1] $end
$var wire 1 f carry_w [0] $end
$var wire 1 g generate_w [15] $end
$var wire 1 h generate_w [14] $end
$var wire 1 i generate_w [13] $end
$var wire 1 j generate_w [12] $end
$var wire 1 k generate_w [11] $end
$var wire 1 l generate_w [10] $end
$var wire 1 m generate_w [9] $end
$var wire 1 n generate_w [8] $end
$var wire 1 o generate_w [7] $end
$var wire 1 p generate_w [6] $end
$var wire 1 q generate_w [5] $end
$var wire 1 r generate_w [4] $end
$var wire 1 s generate_w [3] $end
$var wire 1 t generate_w [2] $end
$var wire 1 u generate_w [1] $end
$var wire 1 v generate_w [0] $end
$var wire 1 w propagate_w [15] $end
$var wire 1 x propagate_w [14] $end
$var wire 1 y propagate_w [13] $end
$var wire 1 z propagate_w [12] $end
$var wire 1 { propagate_w [11] $end
$var wire 1 | propagate_w [10] $end
$var wire 1 } propagate_w [9] $end
$var wire 1 ~ propagate_w [8] $end
$var wire 1 !! propagate_w [7] $end
$var wire 1 "! propagate_w [6] $end
$var wire 1 #! propagate_w [5] $end
$var wire 1 $! propagate_w [4] $end
$var wire 1 %! propagate_w [3] $end
$var wire 1 &! propagate_w [2] $end
$var wire 1 '! propagate_w [1] $end
$var wire 1 (! propagate_w [0] $end
$var wire 1 )! sum_w [15] $end
$var wire 1 *! sum_w [14] $end
$var wire 1 +! sum_w [13] $end
$var wire 1 ,! sum_w [12] $end
$var wire 1 -! sum_w [11] $end
$var wire 1 .! sum_w [10] $end
$var wire 1 /! sum_w [9] $end
$var wire 1 0! sum_w [8] $end
$var wire 1 1! sum_w [7] $end
$var wire 1 2! sum_w [6] $end
$var wire 1 3! sum_w [5] $end
$var wire 1 4! sum_w [4] $end
$var wire 1 5! sum_w [3] $end
$var wire 1 6! sum_w [2] $end
$var wire 1 7! sum_w [1] $end
$var wire 1 8! sum_w [0] $end
$scope begin genblk2[15] $end
$var parameter 32 9! j $end
$upscope $end
$scope begin genblk2[14] $end
$var parameter 32 :! j $end
$upscope $end
$scope begin genblk2[13] $end
$var parameter 32 ;! j $end
$upscope $end
$scope begin genblk2[12] $end
$var parameter 32 <! j $end
$upscope $end
$scope begin genblk2[11] $end
$var parameter 32 =! j $end
$upscope $end
$scope begin genblk2[10] $end
$var parameter 32 >! j $end
$upscope $end
$scope begin genblk2[9] $end
$var parameter 32 ?! j $end
$upscope $end
$scope begin genblk2[8] $end
$var parameter 32 @! j $end
$upscope $end
$scope begin genblk2[7] $end
$var parameter 32 A! j $end
$upscope $end
$scope begin genblk2[6] $end
$var parameter 32 B! j $end
$upscope $end
$scope begin genblk2[5] $end
$var parameter 32 C! j $end
$upscope $end
$scope begin genblk2[4] $end
$var parameter 32 D! j $end
$upscope $end
$scope begin genblk2[3] $end
$var parameter 32 E! j $end
$upscope $end
$scope begin genblk2[2] $end
$var parameter 32 F! j $end
$upscope $end
$scope begin genblk2[1] $end
$var parameter 32 G! j $end
$upscope $end
$scope begin genblk2[0] $end
$var parameter 32 H! j $end
$upscope $end
$scope begin genblk1[15] $end
$var parameter 32 I! i $end
$scope begin genblk1 $end
$upscope $end
$upscope $end
$scope begin genblk1[14] $end
$var parameter 32 J! i $end
$scope begin genblk1 $end
$upscope $end
$upscope $end
$scope begin genblk1[13] $end
$var parameter 32 K! i $end
$scope begin genblk1 $end
$upscope $end
$upscope $end
$scope begin genblk1[12] $end
$var parameter 32 L! i $end
$scope begin genblk1 $end
$upscope $end
$upscope $end
$scope begin genblk1[11] $end
$var parameter 32 M! i $end
$scope begin genblk1 $end
$upscope $end
$upscope $end
$scope begin genblk1[10] $end
$var parameter 32 N! i $end
$scope begin genblk1 $end
$upscope $end
$upscope $end
$scope begin genblk1[9] $end
$var parameter 32 O! i $end
$scope begin genblk1 $end
$upscope $end
$upscope $end
$scope begin genblk1[8] $end
$var parameter 32 P! i $end
$scope begin genblk1 $end
$upscope $end
$upscope $end
$scope begin genblk1[7] $end
$var parameter 32 Q! i $end
$scope begin genblk1 $end
$upscope $end
$upscope $end
$scope begin genblk1[6] $end
$var parameter 32 R! i $end
$scope begin genblk1 $end
$upscope $end
$upscope $end
$scope begin genblk1[5] $end
$var parameter 32 S! i $end
$scope begin genblk1 $end
$upscope $end
$upscope $end
$scope begin genblk1[4] $end
$var parameter 32 T! i $end
$scope begin genblk1 $end
$upscope $end
$upscope $end
$scope begin genblk1[3] $end
$var parameter 32 U! i $end
$scope begin genblk1 $end
$upscope $end
$upscope $end
$scope begin genblk1[2] $end
$var parameter 32 V! i $end
$scope begin genblk1 $end
$upscope $end
$upscope $end
$scope begin genblk1[1] $end
$var parameter 32 W! i $end
$scope begin genblk1 $end
$upscope $end
$upscope $end
$scope begin genblk1[0] $end
$var parameter 32 X! i $end
$scope begin genblk1 $end
$upscope $end
$upscope $end
$scope unknown genblk1 $end
$upscope $end
$scope unknown genblk2 $end
$upscope $end
$upscope $end
$upscope $end
$enddefinitions $end
#0
$dumpvars
b10000 4
b100 5
b0 X!
b1 W!
b10 V!
b11 U!
b100 T!
b101 S!
b110 R!
b111 Q!
b1000 P!
b1001 O!
b1010 N!
b1011 M!
b1100 L!
b1101 K!
b1110 J!
b1111 I!
b0 H!
b1 G!
b10 F!
b11 E!
b100 D!
b101 C!
b110 B!
b111 A!
b1000 @!
b1001 ?!
b1010 >!
b1011 =!
b1100 <!
b1101 ;!
b1110 :!
b1111 9!
b0 !
b0 "
03
02
01
00
0/
0.
0-
0,
0+
0*
0)
0(
0'
0&
0%
0$
0#
0f
0e
0d
0c
0b
0a
0`
0_
0^
0]
0\
0[
0Z
0Y
0X
0W
0V
0v
0u
0t
0s
0r
0q
0p
0o
0n
0m
0l
0k
0j
0i
0h
0g
0(!
0'!
0&!
0%!
0$!
0#!
0"!
0!!
0~
0}
0|
0{
0z
0y
0x
0w
08!
07!
06!
05!
04!
03!
02!
01!
00!
0/!
0.!
0-!
0,!
0+!
0*!
0)!
0U
0T
0S
0R
0Q
0P
0O
0N
0M
0L
0K
0J
0I
0H
0G
0F
0E
0D
0C
0B
0A
0@
0?
0>
0=
0<
0;
0:
09
08
07
06
$end
#10000
b10100110101111 !
b111101000011011 "
1U
1T
1R
1Q
1L
1J
1I
1H
1G
1E
1D
1C
1B
1@
1>
1=
1:
18
1i
1k
10!
1~
11!
1!!
13!
1#!
1s
1&!
1u
1v
1*!
1x
1y
1,!
1z
1{
1/!
1}
14!
1$!
1%!
1'!
1(!
1e
1d
1b
1Z
1X
0*!
1W
0,!
1Y
04!
1a
1c
17!
15!
03!
1`
1+!
1)!
12!
12
10
1-
1,
1+
1*
1&
1$
#20000
b1000100000000 !
b1000100010001 "
0T
0R
1M
0L
0J
0H
0G
0E
0D
0C
0B
0@
0>
0:
19
08
0y
1,!
1j
0{
01!
0!!
13!
0#!
0%!
16!
0&!
0'!
0v
1*!
0x
0i
0k
0/!
0}
00!
1n
0s
0u
0d
0b
1]
0Z
0X
0W
0e
0c
0`
02!
05!
07!
0)!
0*!
0,!
1/!
14!
0a
06!
03!
02
00
1/
0-
0,
0+
0$
#30000
b1000000100010110 !
b1110011001110 "
0U
1T
1S
1R
0Q
1O
1N
0M
1K
1J
1D
1C
1A
09
16
1)!
1w
1,!
0j
1t
1u
1-!
1{
1.!
1|
10!
0n
11!
1!!
12!
1"!
1%!
1&!
1'!
0(!
0]
1d
1c
0Y
0+!
1b
16!
0/!
04!
1a
13!
11
0/
1.
1-
1,
1+
0*
1)
1(
1'
0&
1$
#35000
b100010010000010 !
b11101111001101 "
1U
0T
1M
1L
0K
1H
0C
0A
1>
0=
1;
17
06
0)!
0w
1*!
1x
01!
1o
14!
0$!
06!
0t
1+!
1y
1/!
1}
0u
1(!
0d
0a
1^
00!
1]
03!
0c
0b
0/!
1\
0.!
1[
04!
0-!
1Z
0,!
1Y
0+!
1X
0*!
1W
1)!
01
0.
0,
0+
0)
0(
0'
#37000
b1000100101000011 !
b1111111111111111 "
1T
1Q
1P
1K
1G
1F
1E
1?
0>
1=
0;
1:
07
16
1g
1-!
1k
10!
1n
11!
0o
02!
1p
1v
1w
13!
1#!
14!
1$!
1u
1d
1e
1_
1V
01!
17!
1c
1b
04!
1a
03!
1`
12!
12
1+
1(
1#
#47000
b1010101111001101 !
b0 "
0U
0T
0S
0R
0Q
0P
0O
0N
0M
0L
0K
0J
0I
0H
0G
0F
0D
1C
1B
1>
1<
18
0'!
0)!
0g
1*!
0x
1,!
0z
0-!
0k
1.!
0|
00!
0n
02!
0p
13!
0#!
14!
0$!
0u
0v
0e
0d
0a
0`
0[
0Y
0W
1)!
0V
1+!
0X
1-!
0Z
12!
0_
03!
0c
07!
0b
11!
0^
0,!
0*!
10!
0]
04!
1/!
0\
0.!
02
1,
1*
1&
0#
#57000
b0 !
b1001000110100 "
1S
1Q
1P
1L
1I
0E
0C
0B
0?
0>
0=
0<
0:
08
06
0)!
0w
0+!
0y
0-!
0{
00!
0~
01!
0!!
02!
0"!
0%!
0(!
1,!
1z
13!
1#!
14!
1$!
1/
1.
0-
0,
0+
0(
1'
0&
0$
#67000
b1000100010001 !
b1110111010101010 "
1T
0S
1R
0Q
1N
1K
1J
0I
1H
1G
1F
1E
1A
1=
19
10!
1~
1(!
1)!
1w
1*!
1x
1+!
1y
1-!
1{
1.!
1|
11!
1!!
1%!
0&!
1'!
1,
1+
1)
1(
1&
1%
1$
#77000
b101010101010101 !
b1010101010101010 "
0K
0G
1C
1?
1;
17
12!
1"!
1&!
1-
#87000
b1000000001010001 !
b1000000010000110 "
1S
0R
0P
0L
0J
0H
0C
0=
0;
09
07
16
0)!
1g
0*!
0x
0,!
0z
0.!
0|
00!
0~
0+!
0y
0-!
0{
0/!
0}
03!
0#!
0%!
1V
0.
0+
0*
0)
0(
0'
0&
0%
0$
1#
#92000
b1111101011011100 !
b11011100 "
0T
1R
1Q
1O
0F
0E
1C
1B
1>
1<
1:
19
18
17
1*!
1x
1+!
1y
1,!
1z
1-!
1{
1/!
1}
01!
1o
1s
1t
0(!
1)!
0g
02!
1p
04!
1r
1%!
0'!
1a
1_
0V
1c
1b
1^
10!
14!
15!
11!
13!
10
1.
0-
1+
1*
1(
1'
1&
1%
1$
0#
#94000
b100000010010110 !
b10000001001000 "
0S
0Q
0N
1H
1D
0B
0?
0<
0:
09
08
06
0)!
0w
0,!
0z
0-!
0{
0/!
0}
12!
0p
05!
0s
1'!
01!
0o
04!
0r
0t
0c
0_
11!
0^
0b
14!
0a
00!
03!
00
0.
1-
0+
0*
0(
0'
0$
#104000
b1000000100100 !
b1000000110010010 "
1T
0R
1Q
0O
1N
1M
0H
1F
0D
0A
1@
0>
19
07
0*!
0x
1,!
1z
13!
1#!
1)!
1w
0+!
0y
10!
1~
02!
0"!
0%!
1.
0-
1+
1'
0&
0%
1$
#204000
b0 !
b1 "
1U
0T
0Q
0N
0M
0F
0C
0@
09
0,!
0z
03!
0#!
0&!
0)!
0w
00!
0~
01!
0!!
04!
0$!
0'!
1(!
0/
0.
0,
0+
0'
0$
