multipliers16/traditional_multiplier16/msim/presynth/full_adder.v
`timescale 1ns / 1ps
//////////////////////////////////////////////////////////////////////////////////
// Company: 
// Engineer: 
// 
// Create Date:    15:11:39 06/09/2020 
// Design Name: 
// Module Name:    full_adder 
// Project Name: 
// Target Devices: 
// Tool versions: 
// Description: 
//
// Dependencies: 
//
// Revision: 
// Revision 0.01 - File Created
// Additional Comments: 
//
//////////////////////////////////////////////////////////////////////////////////
module full_adder(input1_i,input2_i,carry_i,sum_o,carry_o);
input input1_i, input2_i;
input carry_i;
output sum_o;
output carry_o;

assign sum_o = input1_i ^ input2_i ^ carry_i;
assign carry_o = (input1_i & input2_i) | (input1_i & carry_i) | (input2_i & carry_i);

endmodule

adders16/carry_lookahead_adder16/snps/carry_lookahead_adder16.v
`timescale 1ns / 1ps
//////////////////////////////////////////////////////////////////////////////////
// Company: 
// Engineer: 
// 
// Create Date:    14:19:28 06/09/2020 
// Design Name: 
// Module Name:    ripple_carry_adder 
// Project Name: 
// Target Devices: 
// Tool versions: 
// Description: 
//
// Dependencies: 
//
// Revision: 
// Revision 0.01 - File Created
// Additional Comments: 
//
//////////////////////////////////////////////////////////////////////////////////
module carry_lookahead_adder16(add1_i,add2_i,result_o);
parameter width =16;
input [width-1:0] add1_i;
input [width-1:0] add2_i;
output [width:0] result_o;

wire [width:0] carry_w;
wire [width-1:0] generate_w, propagate_w, sum_w;


genvar i;

generate
for(i=0; i<width; i = i+1)
begin 
full_adder fa(.input1_i(add1_i[i]), .input2_i(add2_i[i]), .carry_i(carry_w[i]), .sum_o(sum_w[i]), .carry_o());
end

endgenerate

genvar j;

generate
for(j=0; j<width; j = j+1)
begin
assign generate_w[j] = add1_i[j] & add2_i[j];
assign propagate_w[j] = add1_i[j] | add2_i[j];
assign carry_w[j+1] = generate_w[j]| (propagate_w[j] & carry_w[j]);
end

endgenerate

assign carry_w[0] = 1'b1;
assign result_o = {carry_w[width],sum_w};
endmodule

adders16/carry_lookahead_adder16/msim/presynth/carry_lookahead_adder16_tb.v
`timescale 1ns / 1ps
//////////////////////////////////////////////////////////////////////////////////
// Company: 
// Engineer: 
// 
// Create Date: 05/05/2020 01:15:36 AM
// Design Name: 
// Module Name: Test_Bench
// Project Name: 
// Target Devices: 
// Tool Versions: 
// Description: 
// 
// Dependencies: 
// 
// Revision:
// Revision 0.01 - File Created
// Additional Comments:
// 
//////////////////////////////////////////////////////////////////////////////////


module carry_lookahead_adder16_tb;
reg [15:0]add1_i;
reg [15:0]add2_i;
wire [16:0]result_o;


carry_lookahead_adder16 cla(add1_i,add2_i,result_o);

initial begin
   $dumpfile("carry_lookahead_adder16_sim.vcd");
   $dumpvars(2,carry_lookahead_adder16_tb);

   
   add1_i = 16'h0000;
   add2_i = 16'h0000;
   #10
   add1_i = 16'h29AF;
   add2_i = 16'h7A1B;
   #10
   add1_i = 16'h1100;
   add2_i = 16'h1111;
   #10
   add1_i = 16'h8116;
   add2_i = 16'h1CCE;
   #5
   add1_i = 16'h4482;
   add2_i = 16'h3BCD;
   #2
   add1_i = 16'h8943;
   add2_i = 16'hFFFF;
   #10
   add1_i = 16'hABCD;
   add2_i = 16'h0000;
   #10
   add1_i = 16'h0000;
   add2_i = 16'h1234;
   #10
   add1_i = 16'h1111;
   add2_i = 16'hEEAA;
  #10
   add1_i = 16'h5555;
   add2_i = 16'hAAAA;
  #10
   add1_i = 16'h8051;
   add2_i = 16'h8086;
  #5
  add1_i = 16'hFADC;
  add2_i = 16'h00DC;
 #2
  add1_i = 16'h4096;
  add2_i = 16'h2048;
 #10
  add1_i = 16'h1024;
  add2_i = 16'h8192;
  #100
   add1_i = 16'h0000;
   add2_i = 16'h0001;
  #100
  
   $finish;
    
   
 end

initial begin

$monitor($time , " add1_i= %h, add2_i = %h, result_o = %h ",add1_i, add2_i, result_o);
end
	
	
	
endmodule

adders/carry_lookahead_adder16/msim/presynth/carry_lookahead_adder16_sim.vcd
$date
	Fri Jul 31 08:58:14 2020
$end
$version
	ModelSim Version 6.6d
$end
$timescale
	1ps
$end
$scope module carry_lookahead_adder16_tb $end
$var reg 16 ! add1_i [15:0] $end
$var reg 16 " add2_i [15:0] $end
$var wire 1 # result_o [16] $end
$var wire 1 $ result_o [15] $end
$var wire 1 % result_o [14] $end
$var wire 1 & result_o [13] $end
$var wire 1 ' result_o [12] $end
$var wire 1 ( result_o [11] $end
$var wire 1 ) result_o [10] $end
$var wire 1 * result_o [9] $end
$var wire 1 + result_o [8] $end
$var wire 1 , result_o [7] $end
$var wire 1 - result_o [6] $end
$var wire 1 . result_o [5] $end
$var wire 1 / result_o [4] $end
$var wire 1 0 result_o [3] $end
$var wire 1 1 result_o [2] $end
$var wire 1 2 result_o [1] $end
$var wire 1 3 result_o [0] $end
$scope module cla $end
$var parameter 32 4 width $end
$var wire 1 5 add1_i [15] $end
$var wire 1 6 add1_i [14] $end
$var wire 1 7 add1_i [13] $end
$var wire 1 8 add1_i [12] $end
$var wire 1 9 add1_i [11] $end
$var wire 1 : add1_i [10] $end
$var wire 1 ; add1_i [9] $end
$var wire 1 < add1_i [8] $end
$var wire 1 = add1_i [7] $end
$var wire 1 > add1_i [6] $end
$var wire 1 ? add1_i [5] $end
$var wire 1 @ add1_i [4] $end
$var wire 1 A add1_i [3] $end
$var wire 1 B add1_i [2] $end
$var wire 1 C add1_i [1] $end
$var wire 1 D add1_i [0] $end
$var wire 1 E add2_i [15] $end
$var wire 1 F add2_i [14] $end
$var wire 1 G add2_i [13] $end
$var wire 1 H add2_i [12] $end
$var wire 1 I add2_i [11] $end
$var wire 1 J add2_i [10] $end
$var wire 1 K add2_i [9] $end
$var wire 1 L add2_i [8] $end
$var wire 1 M add2_i [7] $end
$var wire 1 N add2_i [6] $end
$var wire 1 O add2_i [5] $end
$var wire 1 P add2_i [4] $end
$var wire 1 Q add2_i [3] $end
$var wire 1 R add2_i [2] $end
$var wire 1 S add2_i [1] $end
$var wire 1 T add2_i [0] $end
$var wire 1 # result_o [16] $end
$var wire 1 $ result_o [15] $end
$var wire 1 % result_o [14] $end
$var wire 1 & result_o [13] $end
$var wire 1 ' result_o [12] $end
$var wire 1 ( result_o [11] $end
$var wire 1 ) result_o [10] $end
$var wire 1 * result_o [9] $end
$var wire 1 + result_o [8] $end
$var wire 1 , result_o [7] $end
$var wire 1 - result_o [6] $end
$var wire 1 . result_o [5] $end
$var wire 1 / result_o [4] $end
$var wire 1 0 result_o [3] $end
$var wire 1 1 result_o [2] $end
$var wire 1 2 result_o [1] $end
$var wire 1 3 result_o [0] $end
$var wire 1 U carry_w [16] $end
$var wire 1 V carry_w [15] $end
$var wire 1 W carry_w [14] $end
$var wire 1 X carry_w [13] $end
$var wire 1 Y carry_w [12] $end
$var wire 1 Z carry_w [11] $end
$var wire 1 [ carry_w [10] $end
$var wire 1 \ carry_w [9] $end
$var wire 1 ] carry_w [8] $end
$var wire 1 ^ carry_w [7] $end
$var wire 1 _ carry_w [6] $end
$var wire 1 ` carry_w [5] $end
$var wire 1 a carry_w [4] $end
$var wire 1 b carry_w [3] $end
$var wire 1 c carry_w [2] $end
$var wire 1 d carry_w [1] $end
$var wire 1 e carry_w [0] $end
$var wire 1 f generate_w [15] $end
$var wire 1 g generate_w [14] $end
$var wire 1 h generate_w [13] $end
$var wire 1 i generate_w [12] $end
$var wire 1 j generate_w [11] $end
$var wire 1 k generate_w [10] $end
$var wire 1 l generate_w [9] $end
$var wire 1 m generate_w [8] $end
$var wire 1 n generate_w [7] $end
$var wire 1 o generate_w [6] $end
$var wire 1 p generate_w [5] $end
$var wire 1 q generate_w [4] $end
$var wire 1 r generate_w [3] $end
$var wire 1 s generate_w [2] $end
$var wire 1 t generate_w [1] $end
$var wire 1 u generate_w [0] $end
$var wire 1 v propagate_w [15] $end
$var wire 1 w propagate_w [14] $end
$var wire 1 x propagate_w [13] $end
$var wire 1 y propagate_w [12] $end
$var wire 1 z propagate_w [11] $end
$var wire 1 { propagate_w [10] $end
$var wire 1 | propagate_w [9] $end
$var wire 1 } propagate_w [8] $end
$var wire 1 ~ propagate_w [7] $end
$var wire 1 !! propagate_w [6] $end
$var wire 1 "! propagate_w [5] $end
$var wire 1 #! propagate_w [4] $end
$var wire 1 $! propagate_w [3] $end
$var wire 1 %! propagate_w [2] $end
$var wire 1 &! propagate_w [1] $end
$var wire 1 '! propagate_w [0] $end
$var wire 1 (! sum_w [15] $end
$var wire 1 )! sum_w [14] $end
$var wire 1 *! sum_w [13] $end
$var wire 1 +! sum_w [12] $end
$var wire 1 ,! sum_w [11] $end
$var wire 1 -! sum_w [10] $end
$var wire 1 .! sum_w [9] $end
$var wire 1 /! sum_w [8] $end
$var wire 1 0! sum_w [7] $end
$var wire 1 1! sum_w [6] $end
$var wire 1 2! sum_w [5] $end
$var wire 1 3! sum_w [4] $end
$var wire 1 4! sum_w [3] $end
$var wire 1 5! sum_w [2] $end
$var wire 1 6! sum_w [1] $end
$var wire 1 7! sum_w [0] $end
$scope begin genblk2[15] $end
$var parameter 32 8! j $end
$upscope $end
$scope begin genblk2[14] $end
$var parameter 32 9! j $end
$upscope $end
$scope begin genblk2[13] $end
$var parameter 32 :! j $end
$upscope $end
$scope begin genblk2[12] $end
$var parameter 32 ;! j $end
$upscope $end
$scope begin genblk2[11] $end
$var parameter 32 <! j $end
$upscope $end
$scope begin genblk2[10] $end
$var parameter 32 =! j $end
$upscope $end
$scope begin genblk2[9] $end
$var parameter 32 >! j $end
$upscope $end
$scope begin genblk2[8] $end
$var parameter 32 ?! j $end
$upscope $end
$scope begin genblk2[7] $end
$var parameter 32 @! j $end
$upscope $end
$scope begin genblk2[6] $end
$var parameter 32 A! j $end
$upscope $end
$scope begin genblk2[5] $end
$var parameter 32 B! j $end
$upscope $end
$scope begin genblk2[4] $end
$var parameter 32 C! j $end
$upscope $end
$scope begin genblk2[3] $end
$var parameter 32 D! j $end
$upscope $end
$scope begin genblk2[2] $end
$var parameter 32 E! j $end
$upscope $end
$scope begin genblk2[1] $end
$var parameter 32 F! j $end
$upscope $end
$scope begin genblk2[0] $end
$var parameter 32 G! j $end
$upscope $end
$scope begin genblk1[15] $end
$var parameter 32 H! i $end
$upscope $end
$scope begin genblk1[14] $end
$var parameter 32 I! i $end
$upscope $end
$scope begin genblk1[13] $end
$var parameter 32 J! i $end
$upscope $end
$scope begin genblk1[12] $end
$var parameter 32 K! i $end
$upscope $end
$scope begin genblk1[11] $end
$var parameter 32 L! i $end
$upscope $end
$scope begin genblk1[10] $end
$var parameter 32 M! i $end
$upscope $end
$scope begin genblk1[9] $end
$var parameter 32 N! i $end
$upscope $end
$scope begin genblk1[8] $end
$var parameter 32 O! i $end
$upscope $end
$scope begin genblk1[7] $end
$var parameter 32 P! i $end
$upscope $end
$scope begin genblk1[6] $end
$var parameter 32 Q! i $end
$upscope $end
$scope begin genblk1[5] $end
$var parameter 32 R! i $end
$upscope $end
$scope begin genblk1[4] $end
$var parameter 32 S! i $end
$upscope $end
$scope begin genblk1[3] $end
$var parameter 32 T! i $end
$upscope $end
$scope begin genblk1[2] $end
$var parameter 32 U! i $end
$upscope $end
$scope begin genblk1[1] $end
$var parameter 32 V! i $end
$upscope $end
$scope begin genblk1[0] $end
$var parameter 32 W! i $end
$upscope $end
$scope unknown genblk1 $end
$upscope $end
$scope unknown genblk2 $end
$upscope $end
$upscope $end
$upscope $end
$enddefinitions $end
#0
$dumpvars
b10000 4
b0 W!
b1 V!
b10 U!
b11 T!
b100 S!
b101 R!
b110 Q!
b111 P!
b1000 O!
b1001 N!
b1010 M!
b1011 L!
b1100 K!
b1101 J!
b1110 I!
b1111 H!
b0 G!
b1 F!
b10 E!
b11 D!
b100 C!
b101 B!
b110 A!
b111 @!
b1000 ?!
b1001 >!
b1010 =!
b1011 <!
b1100 ;!
b1101 :!
b1110 9!
b1111 8!
b0 !
b0 "
03
02
01
00
0/
0.
0-
0,
0+
0*
0)
0(
0'
0&
0%
0$
0#
0e
0d
0c
0b
0a
0`
0_
0^
0]
0\
0[
0Z
0Y
0X
0W
0V
0U
0u
0t
0s
0r
0q
0p
0o
0n
0m
0l
0k
0j
0i
0h
0g
0f
0'!
0&!
0%!
0$!
0#!
0"!
0!!
0~
0}
0|
0{
0z
0y
0x
0w
0v
07!
06!
05!
04!
03!
02!
01!
00!
0/!
0.!
0-!
0,!
0+!
0*!
0)!
0(!
0T
0S
0R
0Q
0P
0O
0N
0M
0L
0K
0J
0I
0H
0G
0F
0E
0D
0C
0B
0A
0@
0?
0>
0=
0<
0;
0:
09
08
07
06
05
$end
#10000
b10100110101111 !
b111101000011011 "
1T
1S
1Q
1P
1K
1I
1H
1G
1F
1D
1C
1B
1A
1?
1=
1<
19
17
1h
1j
1/!
1}
10!
1~
12!
1"!
1r
15!
1%!
1t
1u
1)!
1w
1x
1+!
1y
1z
1.!
1|
13!
1#!
1$!
1&!
1'!
1d
1c
1a
1Y
1W
0)!
1V
0+!
1X
03!
1`
05!
1b
16!
14!
02!
1_
1*!
1(!
11!
12
10
1-
1,
1+
1*
1&
1$
#20000
b1000100000000 !
b1000100010001 "
0S
0Q
1L
0K
0I
0G
0F
0D
0C
0B
0A
0?
0=
09
18
07
0x
1+!
1i
0z
00!
0~
12!
0"!
0$!
15!
0%!
0&!
17!
0u
1)!
0w
0h
0j
0.!
0|
0/!
1m
0r
0t
0c
0a
1\
0Y
0W
0V
0d
0b
0_
01!
04!
06!
0(!
0)!
0+!
1.!
13!
0`
05!
02!
13
02
00
1/
0-
0,
0+
0$
#30000
b1000000100010110 !
b1110011001110 "
0T
1S
1R
1Q
0P
1N
1M
0L
1J
1I
1C
1B
1@
08
15
1(!
1v
1+!
0i
1s
1t
1,!
1z
1-!
1{
1/!
0m
10!
1~
11!
1!!
14!
1$!
1%!
1&!
07!
0'!
0\
1c
1b
0X
0*!
04!
1a
15!
0.!
03!
1`
12!
03
11
0/
1.
1-
1,
1+
0*
1)
1(
1'
0&
1$
#35000
b100010010000010 !
b11101111001101 "
1T
0S
1L
1K
0J
1G
0B
0@
1=
0<
1:
16
05
0(!
0v
1)!
1w
00!
1n
13!
0#!
05!
0s
1*!
1x
1.!
1|
16!
0t
17!
1'!
0c
0`
1]
0/!
1\
02!
15!
0b
14!
0a
0.!
1[
0-!
1Z
03!
0,!
1Y
0+!
1X
0*!
1W
0)!
1V
1(!
13
12
10
0.
0,
0+
0)
0(
0'
#37000
b1000100101000011 !
b1111111111111111 "
1S
1P
1O
1J
1F
1E
1D
1>
0=
1<
0:
19
06
15
1f
1,!
1j
1/!
1m
10!
0n
01!
1o
07!
1u
1v
12!
1"!
13!
1#!
06!
1t
1c
1d
1^
1U
00!
16!
05!
1b
04!
1a
03!
1`
02!
1_
11!
03
01
00
1+
1(
1#
#47000
b1010101111001101 !
b0 "
0T
0S
0R
0Q
0P
0O
0N
0M
0L
0K
0J
0I
0H
0G
0F
0E
0C
1B
1A
1=
1;
17
0&!
0(!
0f
1)!
0w
1+!
0y
0,!
0j
1-!
0{
0/!
0m
01!
0o
12!
0"!
13!
0#!
0t
17!
0u
0d
0c
0`
0_
0Z
0X
0V
1(!
0U
1*!
0W
1,!
0Y
11!
0^
02!
15!
0b
06!
14!
0a
10!
0]
0+!
0)!
1/!
0\
03!
1.!
0[
0-!
13
02
11
10
1,
1*
1&
0#
#57000
b0 !
b1001000110100 "
1R
1P
1O
1K
1H
0D
0B
0A
0>
0=
0<
0;
09
07
05
0(!
0v
0*!
0x
0,!
0z
0/!
0}
00!
0~
01!
0!!
04!
0$!
07!
0'!
1+!
1y
12!
1"!
13!
1#!
03
00
1/
1.
0-
0,
0+
0(
1'
0&
0$
#67000
b1000100010001 !
b1110111010101010 "
1S
0R
1Q
0P
1M
1J
1I
0H
1G
1F
1E
1D
1@
1<
18
1/!
1}
17!
1'!
1(!
1v
1)!
1w
1*!
1x
1,!
1z
1-!
1{
10!
1~
14!
1$!
05!
0%!
16!
1&!
13
12
01
10
1,
1+
1)
1(
1&
1%
1$
#77000
b101010101010101 !
b1010101010101010 "
0J
0F
1B
1>
1:
16
11!
1!!
15!
1%!
11
1-
#87000
b1000000001010001 !
b1000000010000110 "
1R
0Q
0O
0K
0I
0G
0B
0<
0:
08
06
15
0(!
1f
0)!
0w
0+!
0y
0-!
0{
0/!
0}
0*!
0x
0,!
0z
0.!
0|
02!
0"!
04!
0$!
1U
00
0.
0+
0*
0)
0(
0'
0&
0%
0$
1#
#92000
b1111101011011100 !
b11011100 "
0S
1Q
1P
1N
0E
0D
1B
1A
1=
1;
19
18
17
16
1)!
1w
1*!
1x
1+!
1y
1,!
1z
1.!
1|
00!
1n
1r
05!
1s
07!
0'!
1(!
0f
01!
1o
03!
1q
1$!
06!
0&!
1`
1^
0U
1b
1a
1]
1/!
13!
14!
10!
12!
03
02
01
10
1.
0-
1+
1*
1(
1'
1&
1%
1$
0#
#94000
b100000010010110 !
b10000001001000 "
0R
0P
0M
1G
1C
0A
0>
0;
09
08
07
05
0(!
0v
0+!
0y
0,!
0z
0.!
0|
11!
0o
04!
0r
16!
1&!
00!
0n
03!
0q
15!
0s
0b
0^
10!
0]
14!
0a
13!
0`
0/!
02!
12
11
0.
1-
0+
0*
0(
0'
0$
#104000
b1000000100100 !
b1000000110010010 "
1S
0Q
1P
0N
1M
1L
0G
1E
0C
0@
1?
0=
18
06
0)!
0w
1+!
1y
12!
1"!
1(!
1v
0*!
0x
1/!
1}
01!
0!!
04!
0$!
00
1.
0-
1+
1'
0&
0%
1$
