multipliers16/traditional_multiplier16/msim/presynth/full_adder.v
`timescale 1ns / 1ps
//////////////////////////////////////////////////////////////////////////////////
// Company: 
// Engineer: 
// 
// Create Date:    15:11:39 06/09/2020 
// Design Name: 
// Module Name:    full_adder 
// Project Name: 
// Target Devices: 
// Tool versions: 
// Description: 
//
// Dependencies: 
//
// Revision: 
// Revision 0.01 - File Created
// Additional Comments: 
//
//////////////////////////////////////////////////////////////////////////////////
module full_adder(input1_i,input2_i,carry_i,sum_o,carry_o);
input input1_i, input2_i;
input carry_i;
output sum_o;
output carry_o;

assign sum_o = input1_i ^ input2_i ^ carry_i;
assign carry_o = (input1_i & input2_i) | (input1_i & carry_i) | (input2_i & carry_i);

endmodule

adders32/lower_part_or_ripple_carry_adder32/msim/presynth/ripple_carry_adder.v
`timescale 1ns / 1ps
//////////////////////////////////////////////////////////////////////////////////
// Company: 
// Engineer: 
// 
// Create Date:    14:19:28 06/09/2020 
// Design Name: 
// Module Name:    ripple_carry_adder 
// Project Name: 
// Target Devices: 
// Tool versions: 
// Description: 
//
// Dependencies: 
//
// Revision: 
// Revision 0.01 - File Created
// Additional Comments: 
//
//////////////////////////////////////////////////////////////////////////////////
module ripple_carry_adder(add1_i, add2_i, carry_i, result_o);
parameter width =24;
input [width-1:0] add1_i;
input [width-1:0] add2_i;
input carry_i;
output [width:0] result_o;

wire [width-1:0] sum_w;
wire [width:0] carry_w;


assign carry_w[0] = carry_i;

genvar i;

generate
for(i=0; i<width; i = i+1)
begin 
   full_adder fa(.input1_i(add1_i[i]), .input2_i(add2_i[i]), .carry_i(carry_w[i]), .sum_o(sum_w[i]), .carry_o(carry_w[i+1]));
end

endgenerate

assign result_o = {carry_w[width], sum_w};

endmodule

adders32/lower_part_or_ripple_carry_adder32/msim/presynth/lower_part_or_ripple_carry_adder32.v
module lower_part_or_ripple_carry_adder32(add1_i, add2_i, result_o);
  parameter width = 32;
  parameter lower_width = 8;
  
  input [width-1:0] add1_i;
  input [width-1:0] add2_i;
  output [width:0] result_o;
  
  
  wire [width:0] sum_w;
  wire  carry_w;
  
  assign carry_w = add1_i[lower_width-1] & add2_i[lower_width-1];
  
  
  genvar i;
  
  generate
  for(i=0; i<lower_width; i=i+1)
  begin
  assign sum_w[i] = add1_i[i] | add2_i[i];
  end
  endgenerate
        
        
  ripple_carry_adder rca(.add1_i(add1_i[width-1:lower_width]), .add2_i(add2_i[width-1:lower_width]), .carry_i(carry_w), .result_o(sum_w[width:lower_width]));
  
  assign result_o = sum_w;
  
endmodule

adders32/lower_part_or_ripple_carry_adder32/snps/primetime/lower_part_or_ripple_carry_adder32_tb.v
//`timescale 1ns / 1ps
//////////////////////////////////////////////////////////////////////////////////
// Company: 
// Engineer: 
// 
// Create Date: 05/05/2020 01:15:36 AM
// Design Name: 
// Module Name: Test_Bench
// Project Name: 
// Target Devices: 
// Tool Versions: 
// Description: 
// 
// Dependencies: 
// 
// Revision:
// Revision 0.01 - File Created
// Additional Comments:
// 
//////////////////////////////////////////////////////////////////////////////////


module lower_part_or_ripple_carry_adder32_tb;
reg [31:0]add1_i;
reg [31:0]add2_i;
wire [32:0]result_o;


lower_part_or_ripple_carry_adder32 loarca(add1_i,add2_i,result_o);

initial begin
   $dumpfile("lower_part_or_ripple_carry_adder32_gatesim.vcd");
   $dumpvars(3,lower_part_or_ripple_carry_adder32_tb);

   
   add1_i = 32'h0000_0000;
   add2_i = 32'h0000_0000;
   #10
   add1_i = 32'h29AF_2430;
   add2_i = 32'h7A1B_9ABC;
   #10
   add1_i = 32'h1100_3456;
   add2_i = 32'h1111_2323;
   #10
   add1_i = 32'h8116_0873;
   add2_i = 32'h1CCE_0178;
   #5
   add1_i = 32'h2020_2012;
   add2_i = 32'hDEAD_BEEF;
   #8
   add1_i = 32'h8943_DEAF;
   add2_i = 32'hDAAD_BAAD;
   #10
   add1_i = 32'hABCD_1234;
   add2_i = 32'h0000_0000;
   #10
   add1_i = 32'h0000_0000;
   add2_i = 32'h1234_5678;
   #10
   add1_i = 32'h1111_4477;
   add2_i = 32'hEEAA_0000;
  #10
   add1_i = 32'h5555_5555;
   add2_i = 32'hAAAA_AAAA;
  #10
   add1_i = 32'h8051_9860;
   add2_i = 32'h8086_BA3E;
  #5
  add1_i = 32'hFADC_0720;
  add2_i = 32'h00DC_0810;
 #8
  add1_i = 32'h4096_2048;
  add2_i = 32'h2048_4096;
 #10
  add1_i = 32'h1024_2048;
  add2_i = 32'h8192_4096;
  #100
  add1_i = 32'h0000_0001;
  add2_i = 32'hDEAF_BEEF;
  #100
  
   $finish;
    
   
 end

initial begin

$monitor($time , " add1_i= %h, add2_i = %h, result_o = %h ",add1_i, add2_i, result_o);
end
	
	
	
endmodule

adders32/lower_part_or_ripple_carry_adder32/msim/presynth/lower_part_or_ripple_carry_adder32_sim.vcd
$date
	Sun Aug 30 22:11:50 2020
$end
$version
	ModelSim Version 6.6d
$end
$timescale
	1ps
$end
$scope module lower_part_or_ripple_carry_adder32_tb $end
$var reg 32 ! add1_i [31:0] $end
$var reg 32 " add2_i [31:0] $end
$var wire 1 # result_o [32] $end
$var wire 1 $ result_o [31] $end
$var wire 1 % result_o [30] $end
$var wire 1 & result_o [29] $end
$var wire 1 ' result_o [28] $end
$var wire 1 ( result_o [27] $end
$var wire 1 ) result_o [26] $end
$var wire 1 * result_o [25] $end
$var wire 1 + result_o [24] $end
$var wire 1 , result_o [23] $end
$var wire 1 - result_o [22] $end
$var wire 1 . result_o [21] $end
$var wire 1 / result_o [20] $end
$var wire 1 0 result_o [19] $end
$var wire 1 1 result_o [18] $end
$var wire 1 2 result_o [17] $end
$var wire 1 3 result_o [16] $end
$var wire 1 4 result_o [15] $end
$var wire 1 5 result_o [14] $end
$var wire 1 6 result_o [13] $end
$var wire 1 7 result_o [12] $end
$var wire 1 8 result_o [11] $end
$var wire 1 9 result_o [10] $end
$var wire 1 : result_o [9] $end
$var wire 1 ; result_o [8] $end
$var wire 1 < result_o [7] $end
$var wire 1 = result_o [6] $end
$var wire 1 > result_o [5] $end
$var wire 1 ? result_o [4] $end
$var wire 1 @ result_o [3] $end
$var wire 1 A result_o [2] $end
$var wire 1 B result_o [1] $end
$var wire 1 C result_o [0] $end
$scope module loarca $end
$var parameter 32 D width $end
$var parameter 32 E lower_width $end
$var wire 1 F add1_i [31] $end
$var wire 1 G add1_i [30] $end
$var wire 1 H add1_i [29] $end
$var wire 1 I add1_i [28] $end
$var wire 1 J add1_i [27] $end
$var wire 1 K add1_i [26] $end
$var wire 1 L add1_i [25] $end
$var wire 1 M add1_i [24] $end
$var wire 1 N add1_i [23] $end
$var wire 1 O add1_i [22] $end
$var wire 1 P add1_i [21] $end
$var wire 1 Q add1_i [20] $end
$var wire 1 R add1_i [19] $end
$var wire 1 S add1_i [18] $end
$var wire 1 T add1_i [17] $end
$var wire 1 U add1_i [16] $end
$var wire 1 V add1_i [15] $end
$var wire 1 W add1_i [14] $end
$var wire 1 X add1_i [13] $end
$var wire 1 Y add1_i [12] $end
$var wire 1 Z add1_i [11] $end
$var wire 1 [ add1_i [10] $end
$var wire 1 \ add1_i [9] $end
$var wire 1 ] add1_i [8] $end
$var wire 1 ^ add1_i [7] $end
$var wire 1 _ add1_i [6] $end
$var wire 1 ` add1_i [5] $end
$var wire 1 a add1_i [4] $end
$var wire 1 b add1_i [3] $end
$var wire 1 c add1_i [2] $end
$var wire 1 d add1_i [1] $end
$var wire 1 e add1_i [0] $end
$var wire 1 f add2_i [31] $end
$var wire 1 g add2_i [30] $end
$var wire 1 h add2_i [29] $end
$var wire 1 i add2_i [28] $end
$var wire 1 j add2_i [27] $end
$var wire 1 k add2_i [26] $end
$var wire 1 l add2_i [25] $end
$var wire 1 m add2_i [24] $end
$var wire 1 n add2_i [23] $end
$var wire 1 o add2_i [22] $end
$var wire 1 p add2_i [21] $end
$var wire 1 q add2_i [20] $end
$var wire 1 r add2_i [19] $end
$var wire 1 s add2_i [18] $end
$var wire 1 t add2_i [17] $end
$var wire 1 u add2_i [16] $end
$var wire 1 v add2_i [15] $end
$var wire 1 w add2_i [14] $end
$var wire 1 x add2_i [13] $end
$var wire 1 y add2_i [12] $end
$var wire 1 z add2_i [11] $end
$var wire 1 { add2_i [10] $end
$var wire 1 | add2_i [9] $end
$var wire 1 } add2_i [8] $end
$var wire 1 ~ add2_i [7] $end
$var wire 1 !! add2_i [6] $end
$var wire 1 "! add2_i [5] $end
$var wire 1 #! add2_i [4] $end
$var wire 1 $! add2_i [3] $end
$var wire 1 %! add2_i [2] $end
$var wire 1 &! add2_i [1] $end
$var wire 1 '! add2_i [0] $end
$var wire 1 # result_o [32] $end
$var wire 1 $ result_o [31] $end
$var wire 1 % result_o [30] $end
$var wire 1 & result_o [29] $end
$var wire 1 ' result_o [28] $end
$var wire 1 ( result_o [27] $end
$var wire 1 ) result_o [26] $end
$var wire 1 * result_o [25] $end
$var wire 1 + result_o [24] $end
$var wire 1 , result_o [23] $end
$var wire 1 - result_o [22] $end
$var wire 1 . result_o [21] $end
$var wire 1 / result_o [20] $end
$var wire 1 0 result_o [19] $end
$var wire 1 1 result_o [18] $end
$var wire 1 2 result_o [17] $end
$var wire 1 3 result_o [16] $end
$var wire 1 4 result_o [15] $end
$var wire 1 5 result_o [14] $end
$var wire 1 6 result_o [13] $end
$var wire 1 7 result_o [12] $end
$var wire 1 8 result_o [11] $end
$var wire 1 9 result_o [10] $end
$var wire 1 : result_o [9] $end
$var wire 1 ; result_o [8] $end
$var wire 1 < result_o [7] $end
$var wire 1 = result_o [6] $end
$var wire 1 > result_o [5] $end
$var wire 1 ? result_o [4] $end
$var wire 1 @ result_o [3] $end
$var wire 1 A result_o [2] $end
$var wire 1 B result_o [1] $end
$var wire 1 C result_o [0] $end
$var wire 1 (! sum_w [32] $end
$var wire 1 )! sum_w [31] $end
$var wire 1 *! sum_w [30] $end
$var wire 1 +! sum_w [29] $end
$var wire 1 ,! sum_w [28] $end
$var wire 1 -! sum_w [27] $end
$var wire 1 .! sum_w [26] $end
$var wire 1 /! sum_w [25] $end
$var wire 1 0! sum_w [24] $end
$var wire 1 1! sum_w [23] $end
$var wire 1 2! sum_w [22] $end
$var wire 1 3! sum_w [21] $end
$var wire 1 4! sum_w [20] $end
$var wire 1 5! sum_w [19] $end
$var wire 1 6! sum_w [18] $end
$var wire 1 7! sum_w [17] $end
$var wire 1 8! sum_w [16] $end
$var wire 1 9! sum_w [15] $end
$var wire 1 :! sum_w [14] $end
$var wire 1 ;! sum_w [13] $end
$var wire 1 <! sum_w [12] $end
$var wire 1 =! sum_w [11] $end
$var wire 1 >! sum_w [10] $end
$var wire 1 ?! sum_w [9] $end
$var wire 1 @! sum_w [8] $end
$var wire 1 A! sum_w [7] $end
$var wire 1 B! sum_w [6] $end
$var wire 1 C! sum_w [5] $end
$var wire 1 D! sum_w [4] $end
$var wire 1 E! sum_w [3] $end
$var wire 1 F! sum_w [2] $end
$var wire 1 G! sum_w [1] $end
$var wire 1 H! sum_w [0] $end
$var wire 1 I! carry_w $end
$scope begin genblk1[7] $end
$var parameter 32 J! i $end
$upscope $end
$scope begin genblk1[6] $end
$var parameter 32 K! i $end
$upscope $end
$scope begin genblk1[5] $end
$var parameter 32 L! i $end
$upscope $end
$scope begin genblk1[4] $end
$var parameter 32 M! i $end
$upscope $end
$scope begin genblk1[3] $end
$var parameter 32 N! i $end
$upscope $end
$scope begin genblk1[2] $end
$var parameter 32 O! i $end
$upscope $end
$scope begin genblk1[1] $end
$var parameter 32 P! i $end
$upscope $end
$scope begin genblk1[0] $end
$var parameter 32 Q! i $end
$upscope $end
$scope module rca $end
$var parameter 32 R! width $end
$var wire 1 F add1_i [23] $end
$var wire 1 G add1_i [22] $end
$var wire 1 H add1_i [21] $end
$var wire 1 I add1_i [20] $end
$var wire 1 J add1_i [19] $end
$var wire 1 K add1_i [18] $end
$var wire 1 L add1_i [17] $end
$var wire 1 M add1_i [16] $end
$var wire 1 N add1_i [15] $end
$var wire 1 O add1_i [14] $end
$var wire 1 P add1_i [13] $end
$var wire 1 Q add1_i [12] $end
$var wire 1 R add1_i [11] $end
$var wire 1 S add1_i [10] $end
$var wire 1 T add1_i [9] $end
$var wire 1 U add1_i [8] $end
$var wire 1 V add1_i [7] $end
$var wire 1 W add1_i [6] $end
$var wire 1 X add1_i [5] $end
$var wire 1 Y add1_i [4] $end
$var wire 1 Z add1_i [3] $end
$var wire 1 [ add1_i [2] $end
$var wire 1 \ add1_i [1] $end
$var wire 1 ] add1_i [0] $end
$var wire 1 f add2_i [23] $end
$var wire 1 g add2_i [22] $end
$var wire 1 h add2_i [21] $end
$var wire 1 i add2_i [20] $end
$var wire 1 j add2_i [19] $end
$var wire 1 k add2_i [18] $end
$var wire 1 l add2_i [17] $end
$var wire 1 m add2_i [16] $end
$var wire 1 n add2_i [15] $end
$var wire 1 o add2_i [14] $end
$var wire 1 p add2_i [13] $end
$var wire 1 q add2_i [12] $end
$var wire 1 r add2_i [11] $end
$var wire 1 s add2_i [10] $end
$var wire 1 t add2_i [9] $end
$var wire 1 u add2_i [8] $end
$var wire 1 v add2_i [7] $end
$var wire 1 w add2_i [6] $end
$var wire 1 x add2_i [5] $end
$var wire 1 y add2_i [4] $end
$var wire 1 z add2_i [3] $end
$var wire 1 { add2_i [2] $end
$var wire 1 | add2_i [1] $end
$var wire 1 } add2_i [0] $end
$var wire 1 I! carry_i $end
$var wire 1 (! result_o [24] $end
$var wire 1 )! result_o [23] $end
$var wire 1 *! result_o [22] $end
$var wire 1 +! result_o [21] $end
$var wire 1 ,! result_o [20] $end
$var wire 1 -! result_o [19] $end
$var wire 1 .! result_o [18] $end
$var wire 1 /! result_o [17] $end
$var wire 1 0! result_o [16] $end
$var wire 1 1! result_o [15] $end
$var wire 1 2! result_o [14] $end
$var wire 1 3! result_o [13] $end
$var wire 1 4! result_o [12] $end
$var wire 1 5! result_o [11] $end
$var wire 1 6! result_o [10] $end
$var wire 1 7! result_o [9] $end
$var wire 1 8! result_o [8] $end
$var wire 1 9! result_o [7] $end
$var wire 1 :! result_o [6] $end
$var wire 1 ;! result_o [5] $end
$var wire 1 <! result_o [4] $end
$var wire 1 =! result_o [3] $end
$var wire 1 >! result_o [2] $end
$var wire 1 ?! result_o [1] $end
$var wire 1 @! result_o [0] $end
$var wire 1 S! sum_w [23] $end
$var wire 1 T! sum_w [22] $end
$var wire 1 U! sum_w [21] $end
$var wire 1 V! sum_w [20] $end
$var wire 1 W! sum_w [19] $end
$var wire 1 X! sum_w [18] $end
$var wire 1 Y! sum_w [17] $end
$var wire 1 Z! sum_w [16] $end
$var wire 1 [! sum_w [15] $end
$var wire 1 \! sum_w [14] $end
$var wire 1 ]! sum_w [13] $end
$var wire 1 ^! sum_w [12] $end
$var wire 1 _! sum_w [11] $end
$var wire 1 `! sum_w [10] $end
$var wire 1 a! sum_w [9] $end
$var wire 1 b! sum_w [8] $end
$var wire 1 c! sum_w [7] $end
$var wire 1 d! sum_w [6] $end
$var wire 1 e! sum_w [5] $end
$var wire 1 f! sum_w [4] $end
$var wire 1 g! sum_w [3] $end
$var wire 1 h! sum_w [2] $end
$var wire 1 i! sum_w [1] $end
$var wire 1 j! sum_w [0] $end
$var wire 1 k! carry_w [24] $end
$var wire 1 l! carry_w [23] $end
$var wire 1 m! carry_w [22] $end
$var wire 1 n! carry_w [21] $end
$var wire 1 o! carry_w [20] $end
$var wire 1 p! carry_w [19] $end
$var wire 1 q! carry_w [18] $end
$var wire 1 r! carry_w [17] $end
$var wire 1 s! carry_w [16] $end
$var wire 1 t! carry_w [15] $end
$var wire 1 u! carry_w [14] $end
$var wire 1 v! carry_w [13] $end
$var wire 1 w! carry_w [12] $end
$var wire 1 x! carry_w [11] $end
$var wire 1 y! carry_w [10] $end
$var wire 1 z! carry_w [9] $end
$var wire 1 {! carry_w [8] $end
$var wire 1 |! carry_w [7] $end
$var wire 1 }! carry_w [6] $end
$var wire 1 ~! carry_w [5] $end
$var wire 1 !" carry_w [4] $end
$var wire 1 "" carry_w [3] $end
$var wire 1 #" carry_w [2] $end
$var wire 1 $" carry_w [1] $end
$var wire 1 %" carry_w [0] $end
$scope begin genblk1[23] $end
$var parameter 32 &" i $end
$upscope $end
$scope begin genblk1[22] $end
$var parameter 32 '" i $end
$upscope $end
$scope begin genblk1[21] $end
$var parameter 32 (" i $end
$upscope $end
$scope begin genblk1[20] $end
$var parameter 32 )" i $end
$upscope $end
$scope begin genblk1[19] $end
$var parameter 32 *" i $end
$upscope $end
$scope begin genblk1[18] $end
$var parameter 32 +" i $end
$upscope $end
$scope begin genblk1[17] $end
$var parameter 32 ," i $end
$upscope $end
$scope begin genblk1[16] $end
$var parameter 32 -" i $end
$upscope $end
$scope begin genblk1[15] $end
$var parameter 32 ." i $end
$upscope $end
$scope begin genblk1[14] $end
$var parameter 32 /" i $end
$upscope $end
$scope begin genblk1[13] $end
$var parameter 32 0" i $end
$upscope $end
$scope begin genblk1[12] $end
$var parameter 32 1" i $end
$upscope $end
$scope begin genblk1[11] $end
$var parameter 32 2" i $end
$upscope $end
$scope begin genblk1[10] $end
$var parameter 32 3" i $end
$upscope $end
$scope begin genblk1[9] $end
$var parameter 32 4" i $end
$upscope $end
$scope begin genblk1[8] $end
$var parameter 32 5" i $end
$upscope $end
$scope begin genblk1[7] $end
$var parameter 32 6" i $end
$upscope $end
$scope begin genblk1[6] $end
$var parameter 32 7" i $end
$upscope $end
$scope begin genblk1[5] $end
$var parameter 32 8" i $end
$upscope $end
$scope begin genblk1[4] $end
$var parameter 32 9" i $end
$upscope $end
$scope begin genblk1[3] $end
$var parameter 32 :" i $end
$upscope $end
$scope begin genblk1[2] $end
$var parameter 32 ;" i $end
$upscope $end
$scope begin genblk1[1] $end
$var parameter 32 <" i $end
$upscope $end
$scope begin genblk1[0] $end
$var parameter 32 =" i $end
$upscope $end
$scope unknown genblk1 $end
$upscope $end
$upscope $end
$scope unknown genblk1 $end
$upscope $end
$upscope $end
$upscope $end
$enddefinitions $end
#0
$dumpvars
b100000 D
b1000 E
b11000 R!
b0 ="
b1 <"
b10 ;"
b11 :"
b100 9"
b101 8"
b110 7"
b111 6"
b1000 5"
b1001 4"
b1010 3"
b1011 2"
b1100 1"
b1101 0"
b1110 /"
b1111 ."
b10000 -"
b10001 ,"
b10010 +"
b10011 *"
b10100 )"
b10101 ("
b10110 '"
b10111 &"
b0 Q!
b1 P!
b10 O!
b11 N!
b100 M!
b101 L!
b110 K!
b111 J!
b0 !
b0 "
0C
0B
0A
0@
0?
0>
0=
0<
0;
0:
09
08
07
06
05
04
03
02
01
00
0/
0.
0-
0,
0+
0*
0)
0(
0'
0&
0%
0$
0#
0H!
0G!
0F!
0E!
0D!
0C!
0B!
0A!
0@!
0?!
0>!
0=!
0<!
0;!
0:!
09!
08!
07!
06!
05!
04!
03!
02!
01!
00!
0/!
0.!
0-!
0,!
0+!
0*!
0)!
0(!
0I!
0j!
0i!
0h!
0g!
0f!
0e!
0d!
0c!
0b!
0a!
0`!
0_!
0^!
0]!
0\!
0[!
0Z!
0Y!
0X!
0W!
0V!
0U!
0T!
0S!
0%"
0$"
0#"
0""
0!"
0~!
0}!
0|!
0{!
0z!
0y!
0x!
0w!
0v!
0u!
0t!
0s!
0r!
0q!
0p!
0o!
0n!
0m!
0l!
0k!
0'!
0&!
0%!
0$!
0#!
0"!
0!!
0~
0}
0|
0{
0z
0y
0x
0w
0v
0u
0t
0s
0r
0q
0p
0o
0n
0m
0l
0k
0j
0i
0h
0g
0f
0e
0d
0c
0b
0a
0`
0_
0^
0]
0\
0[
0Z
0Y
0X
0W
0V
0U
0T
0S
0R
0Q
0P
0O
0N
0M
0L
0K
0J
0I
0H
0G
0F
$end
#10000
b101001101011110010010000110000 !
b1111010000110111001101010111100 "
1%!
1$!
1#!
1"!
1~
1|
1z
1y
1v
1u
1t
1r
1q
1l
1j
1i
1h
1g
1a
1`
1[
1X
1U
1T
1S
1R
1P
1N
1M
1J
1H
1m!
1o!
1Z!
1[!
1]!
1w!
1`!
1y!
1z!
1e!
1h!
1Y!
1a!
1c!
1f!
1g!
1i!
1A!
1C!
1D!
1E!
1F!
0`!
1x!
1v!
1n!
1l!
1S!
1U!
0]!
1u!
1_!
1\!
1A
1@
1?
1>
1<
1?!
1>!
1=!
1<!
1;!
19!
17!
15!
12!
11!
10!
1/!
1+!
1)!
1:
19
18
17
16
14
12
10
1-
1,
1+
1*
1&
1$
#20000
b10001000000000011010001010110 !
b10001000100010010001100100011 "
1'!
1&!
0%!
0$!
0#!
0~
1}
0z
0y
1x
0v
0t
0r
1m
0l
0j
0h
0g
1d
1c
0`
1_
1Y
0U
0T
0S
0R
0P
0N
0J
1I
0H
0m!
1V!
0[!
1]!
0u!
0w!
1`!
0x!
0y!
1b!
0z!
1B!
0l!
0o!
0Y!
0Z!
1r!
0_!
0a!
0c!
0e!
1}!
0g!
1j!
0A!
0E!
1G!
1H!
1d!
1Y!
0V!
0S!
0`!
1^!
0v!
0\!
0]!
1C
1B
0@
1=
0<
1@!
0=!
0;!
1:!
09!
18!
07!
05!
14!
02!
01!
00!
0)!
1;
08
06
15
04
13
02
00
1/
0-
0,
0+
0$
#30000
b10000001000101100000100001110011 !
b11100110011100000000101111000 "
0'!
0&!
1$!
1#!
1!!
0|
0x
0u
1t
1s
1r
0q
1o
1n
0m
1k
1j
1e
0c
1`
0[
1Z
0Y
0X
1T
1S
1Q
0I
1F
1S!
1V!
0n!
1x!
1y!
0f!
1g!
0h!
0F!
1W!
1X!
1Z!
0r!
1[!
1\!
1`!
0b!
0}!
0i!
1E!
0d!
0Y!
1w!
0U!
0^!
1v!
1]!
0A
1@
0?!
0>!
1=!
0<!
0:!
08!
16!
04!
13!
12!
11!
10!
0/!
1.!
1-!
1,!
0+!
1)!
0:
09
18
07
05
03
11
0/
1.
1-
1,
1+
0*
1)
1(
1'
0&
1$
#35000
b100000001000000010000000010010 !
b11011110101011011011111011101111 "
1'!
1&!
1%!
0#!
1~
0}
1|
1{
1z
1y
1x
1v
1u
0t
1p
0o
1l
1g
1f
0e
0`
0_
0Z
1X
0T
0S
0Q
1P
0M
1H
0F
1U!
0Z!
1^!
0v!
0`!
1}!
1T!
1Y!
0\!
0]!
1u!
0y!
1b!
1c!
1f!
1h!
1i!
0j!
1A!
1F!
1`!
0x!
1\!
1d!
1_!
0w!
0^!
1A
1<
0@!
1?!
1>!
1<!
1:!
19!
18!
15!
03!
00!
1/!
1+!
1*!
0;
1:
19
17
15
14
13
10
0.
0+
1*
1&
1%
#43000
b10001001010000111101111010101111 !
b11011010101011011011101010101101 "
0&!
0!!
0{
0k
1e
1c
1b
0a
1`
1^
1\
1[
1Z
1Y
0X
1W
1V
1U
1T
0P
1O
1M
1J
0H
1F
0S!
1k!
0U!
0W!
1o!
1Z!
0\!
1t!
1]!
0u!
1a!
0b!
1z!
0c!
1{!
0d!
1|!
1e!
0}!
0f!
1~!
0g!
1!"
0i!
1#"
1I!
0D!
0X!
0h!
0B!
1%"
1""
1f!
0e!
1}!
1c!
1b!
0a!
1y!
1\!
0t!
0V!
1n!
1U!
0`!
1x!
1g!
1j!
0_!
1w!
1^!
0?
0=
1@!
0?!
0>!
0:!
06!
05!
14!
13!
10!
0.!
0-!
0,!
0)!
1(!
1;
0:
09
05
01
00
1/
1.
1+
0)
0(
0'
0$
1#
#53000
b10101011110011010001001000110100 !
b0 "
0'!
0%!
0$!
0"!
0~
0|
0z
0y
0x
0v
0u
0s
0r
0p
0n
0l
0j
0i
0g
0f
0e
0d
0b
1a
0^
0[
0Z
0W
0V
0T
1S
1R
1N
1L
1H
0U!
1m!
1a!
0y!
0{!
1d!
0|!
0!"
1h!
0""
0A!
1D!
0E!
0G!
0H!
1S!
0k!
1V!
0n!
1W!
0o!
0]!
1`!
0x!
0c!
1e!
0}!
0g!
1i!
0#"
0I!
0%"
0h!
0d!
1_!
0w!
0V!
1U!
0m!
0~!
0z!
0a!
0e!
0T!
0^!
0j!
0C
0B
0@
1?
0<
0@!
1?!
0=!
09!
16!
15!
04!
03!
1-!
0*!
1)!
0(!
0;
1:
08
04
11
10
0/
0.
1(
0%
1$
0#
#63000
b0 !
b10010001101000101011001111000 "
1$!
1#!
1"!
1!!
1|
1{
1y
1w
1s
1q
1p
1l
1i
0c
0a
0`
0\
0Y
0U
0S
0R
0O
0N
0M
0L
0J
0H
0F
0S!
0U!
0W!
0Z!
0[!
0\!
0_!
0b!
0F!
1V!
1]!
1^!
1d!
1h!
1B!
1E!
0A
1@
1=
1>!
1:!
08!
05!
14!
13!
02!
01!
00!
0-!
1,!
0+!
0)!
19
15
03
00
1/
1.
0-
0,
0+
0(
1'
0&
0$
#73000
b10001000100010100010001110111 !
b11101110101010100000000000000000 "
0$!
0#!
0"!
0!!
0|
0{
0y
0w
1t
0s
1r
0q
1n
1k
1j
0i
1h
1g
1f
1e
1d
1c
1a
1`
1_
1[
1W
1U
1Q
1M
1I
1Z!
1b!
1F!
1G!
1H!
1S!
1T!
1U!
1W!
1X!
1[!
1_!
0`!
1a!
0f!
0i!
0E!
1C
1B
1A
0@
0?!
0<!
18!
17!
06!
15!
11!
10!
1.!
1-!
1+!
1*!
1)!
0:
07
13
12
01
10
1,
1+
1)
1(
1&
1%
1$
#83000
b1010101010101010101010101010101 !
b10101010101010101010101010101010 "
1&!
1$!
1"!
1~
1|
1z
1x
1v
0k
0g
0d
0`
1]
1Y
1S
1O
1K
1G
1\!
1`!
1f!
1j!
1c!
1e!
1g!
1i!
1A!
1E!
1@
1<
1@!
1?!
1=!
1<!
1;!
19!
16!
12!
1;
1:
18
17
16
14
11
1-
#93000
b10000000010100011001100001100000 !
b10000000100001101011101000111110 "
1%!
1#!
0~
1y
1s
0r
0p
0l
0j
0h
0e
0c
0a
1`
0]
0[
1Z
0W
1V
0S
0M
0K
0I
0G
1F
0S!
1k!
0T!
0V!
0X!
0Z!
0c!
1{!
0d!
0g!
1!"
0h!
0j!
0H!
0U!
0W!
0Y!
0]!
0_!
1~!
0A!
0e!
1}!
0b!
1z!
0a!
1y!
1d!
0`!
1x!
1_!
0C
0<
0@!
0>!
0=!
0;!
09!
08!
07!
06!
03!
00!
0/!
0.!
0-!
0,!
0+!
0*!
0)!
1(!
0;
09
08
06
04
03
02
01
0.
0+
0*
0)
0(
0'
0&
0%
0$
1#
#98000
b11111010110111000000011100100000 !
b110111000000100000010000 "
0&!
0%!
0$!
0"!
0|
0y
0x
0v
0t
1r
1q
1o
0f
0_
1]
1\
1[
0Z
0Y
0V
0U
1S
1R
1N
1L
1J
1I
1H
1G
1T!
1U!
1V!
1W!
1Y!
0[!
1s!
1`!
1b!
0z!
0~!
1g!
0!"
1h!
1j!
0B!
1S!
0k!
0\!
1t!
0^!
1v!
1w!
0y!
0{!
0}!
0f!
0E!
0F!
0G!
0d!
0b!
0`!
1^!
1]!
1[!
1Z!
0B
0A
0@
0=
1@!
1>!
1=!
0<!
0:!
13!
02!
10!
1/!
1-!
1,!
1+!
1*!
1)!
0(!
1;
19
18
07
05
1.
0-
1+
1*
1(
1'
1&
1%
1$
0#
#106000
b1000000100101100010000001001000 !
b100000010010000100000010010110 "
1&!
1%!
1~
0z
1w
0s
0q
0n
1h
1b
0`
1_
0]
0\
0[
1X
1T
0R
0O
0L
0J
0I
0H
0F
0S!
0V!
0W!
0Y!
1\!
0t!
0_!
1a!
1e!
0h!
0i!
0j!
1B!
0C!
1E!
0^!
1`!
0x!
1d!
0g!
1A!
1F!
1G!
1_!
0w!
0s!
0Z!
1^!
0v!
0]!
1B
1A
1@
0>
1=
1<
0@!
0?!
0>!
0=!
1;!
1:!
17!
16!
03!
12!
00!
0/!
0-!
0,!
0)!
0;
0:
09
08
16
15
12
11
0.
1-
0+
0*
0(
0'
0$
#116000
b10000001001000010000001001000 !
b10000001100100100100000010010110 "
1t
0r
1q
0o
1n
1m
0h
1f
0T
0Q
1P
0N
1I
0G
0T!
1V!
1]!
1S!
0U!
1Z!
0\!
0_!
05!
13!
02!
10!
1,!
0+!
0*!
1)!
00
1.
0-
1+
1'
0&
0%
1$
#216000
b1 !
b11011110101011111011111011101111 "
1'!
1$!
0#!
1"!
1!!
1|
1{
1z
1y
1x
0w
1v
1u
1s
1r
0q
1p
0m
1l
1k
1j
1i
1g
1e
0b
0_
0X
0S
0P
0I
1T!
1W!
1X!
1Y!
0Z!
0^!
1_!
1b!
1c!
0d!
1f!
1g!
1h!
1i!
1C!
0D!
1H!
1C
0?
1>
1?!
1>!
1=!
1<!
0:!
19!
18!
15!
04!
00!
1/!
1.!
1-!
1*!
1:
19
18
17
05
14
13
10
0/
0+
1*
1)
1(
1%
