multipliers16/traditional_multiplier16/msim/presynth/full_adder.v
`timescale 1ns / 1ps
//////////////////////////////////////////////////////////////////////////////////
// Company: 
// Engineer: 
// 
// Create Date:    15:11:39 06/09/2020 
// Design Name: 
// Module Name:    full_adder 
// Project Name: 
// Target Devices: 
// Tool versions: 
// Description: 
//
// Dependencies: 
//
// Revision: 
// Revision 0.01 - File Created
// Additional Comments: 
//
//////////////////////////////////////////////////////////////////////////////////
module full_adder(input1_i,input2_i,carry_i,sum_o,carry_o);
input input1_i, input2_i;
input carry_i;
output sum_o;
output carry_o;

assign sum_o = input1_i ^ input2_i ^ carry_i;
assign carry_o = (input1_i & input2_i) | (input1_i & carry_i) | (input2_i & carry_i);

endmodule

adders/lower_part_or_ripple_carry_adder16/msim/presynth/ripple_carry_adder.v
`timescale 1ns / 1ps
//////////////////////////////////////////////////////////////////////////////////
// Company: 
// Engineer: 
// 
// Create Date:    14:19:28 06/09/2020 
// Design Name: 
// Module Name:    ripple_carry_adder 
// Project Name: 
// Target Devices: 
// Tool versions: 
// Description: 
//
// Dependencies: 
//
// Revision: 
// Revision 0.01 - File Created
// Additional Comments: 
//
//////////////////////////////////////////////////////////////////////////////////
module ripple_carry_adder(add1_i, add2_i, carry_i, result_o);
parameter width =12;
input [width-1:0] add1_i;
input [width-1:0] add2_i;
input carry_i;
output [width:0] result_o;

wire [width-1:0] sum_w;
wire [width:0] carry_w;


assign carry_w[0] = carry_i;

genvar i;

generate
for(i=0; i<width; i = i+1)
begin 
   full_adder fa(.input1_i(add1_i[i]), .input2_i(add2_i[i]), .carry_i(carry_w[i]), .sum_o(sum_w[i]), .carry_o(carry_w[i+1]));
end

endgenerate

assign result_o = {carry_w[width], sum_w};

endmodule

adders32/lower_part_or_ripple_carry_adder32/snps/lower_part_or_ripple_carry_adder32.v
module lower_part_or_ripple_carry_adder16(add1_i, add2_i, result_o);
  parameter width = 32;
  parameter lower_width = 8;
  
  input [width-1:0] add1_i;
  input [width-1:0] add2_i;
  output [width:0] result_o;
  
  
  wire [width:0] sum_w;
  wire  carry_w;
  
  assign carry_w = add1_i[lower_width-1] & add2_i[lower_width-1];
  
  
  genvar i;
  
  generate
  for(i=0; i<lower_width; i=i+1)
  begin
  assign sum_w[i] = add1_i[i] | add2_i[i];
  end
  endgenerate
        
        
  ripple_carry_adder rca(.add1_i(add1_i[width-1:lower_width]), .add2_i(add2_i[width-1:lower_width]), .carry_i(carry_w), .result_o(sum_w[width:lower_width]));
  
  assign result_o = sum_w;
  
endmodule

adders16/lower_part_or_ripple_carry_adder16/msim/presynth/lower_part_or_ripple_carry_adder16_tb.v
`timescale 1ns / 1ps
//////////////////////////////////////////////////////////////////////////////////
// Company: 
// Engineer: 
// 
// Create Date: 05/05/2020 01:15:36 AM
// Design Name: 
// Module Name: Test_Bench
// Project Name: 
// Target Devices: 
// Tool Versions: 
// Description: 
// 
// Dependencies: 
// 
// Revision:
// Revision 0.01 - File Created
// Additional Comments:
// 
//////////////////////////////////////////////////////////////////////////////////


module lower_part_or_ripple_carry_adder16_tb;
reg [15:0]add1_i;
reg [15:0]add2_i;
wire [16:0]result_o;


lower_part_or_ripple_carry_adder16 laorca
(add1_i,add2_i,result_o);

initial begin
   $dumpfile("lower_part_or_ripple_carry_adder16_sim.vcd");
   $dumpvars(3,lower_part_or_ripple_carry_adder16_tb);

   
   add1_i = 16'h0000;
   add2_i = 16'h0000;
   #10
   add1_i = 16'h29AF;
   add2_i = 16'h7A1B;
   #10
   add1_i = 16'h1100;
   add2_i = 16'h1111;
   #10
   add1_i = 16'h8116;
   add2_i = 16'h1CCE;
   #5
   add1_i = 16'h4482;
   add2_i = 16'h3BCD;
   #5
   add1_i = 16'h8943;
   add2_i = 16'hFFFF;
   #10
   add1_i = 16'hABCD;
   add2_i = 16'h0000;
   #10
   add1_i = 16'h0000;
   add2_i = 16'h1234;
   #10
   add1_i = 16'h1111;
   add2_i = 16'hEEAA;
  #10
   add1_i = 16'h5555;
   add2_i = 16'hAAAA;
  #10
   add1_i = 16'h8051;
   add2_i = 16'h8086;
  #5
  add1_i = 16'hFADC;
  add2_i = 16'h00DC;
 #5
  add1_i = 16'h4096;
  add2_i = 16'h2048;
 #10
  add1_i = 16'h1024;
  add2_i = 16'h8192;
  #100
   add1_i = 16'h0000;
   add2_i = 16'h0001;
  #100
  
   $finish;
    
   
 end

initial begin

$monitor($time , " add1_i= %h, add2_i = %h, result_o = %h ",add1_i, add2_i, result_o);
end
	
	
	
endmodule

adders/lower_part_or_ripple_carry_adder16/msim/presynth/lower_part_or_ripple_carry_adder16_sim.vcd
$date
	Wed Aug  5 18:50:06 2020
$end
$version
	ModelSim Version 6.6d
$end
$timescale
	1ps
$end
$scope module lower_part_or_ripple_carry_adder16_tb $end
$var reg 16 ! add1_i [15:0] $end
$var reg 16 " add2_i [15:0] $end
$var wire 1 # result_o [16] $end
$var wire 1 $ result_o [15] $end
$var wire 1 % result_o [14] $end
$var wire 1 & result_o [13] $end
$var wire 1 ' result_o [12] $end
$var wire 1 ( result_o [11] $end
$var wire 1 ) result_o [10] $end
$var wire 1 * result_o [9] $end
$var wire 1 + result_o [8] $end
$var wire 1 , result_o [7] $end
$var wire 1 - result_o [6] $end
$var wire 1 . result_o [5] $end
$var wire 1 / result_o [4] $end
$var wire 1 0 result_o [3] $end
$var wire 1 1 result_o [2] $end
$var wire 1 2 result_o [1] $end
$var wire 1 3 result_o [0] $end
$scope module laorca $end
$var parameter 32 4 width $end
$var parameter 32 5 lower_width $end
$var wire 1 6 add1_i [15] $end
$var wire 1 7 add1_i [14] $end
$var wire 1 8 add1_i [13] $end
$var wire 1 9 add1_i [12] $end
$var wire 1 : add1_i [11] $end
$var wire 1 ; add1_i [10] $end
$var wire 1 < add1_i [9] $end
$var wire 1 = add1_i [8] $end
$var wire 1 > add1_i [7] $end
$var wire 1 ? add1_i [6] $end
$var wire 1 @ add1_i [5] $end
$var wire 1 A add1_i [4] $end
$var wire 1 B add1_i [3] $end
$var wire 1 C add1_i [2] $end
$var wire 1 D add1_i [1] $end
$var wire 1 E add1_i [0] $end
$var wire 1 F add2_i [15] $end
$var wire 1 G add2_i [14] $end
$var wire 1 H add2_i [13] $end
$var wire 1 I add2_i [12] $end
$var wire 1 J add2_i [11] $end
$var wire 1 K add2_i [10] $end
$var wire 1 L add2_i [9] $end
$var wire 1 M add2_i [8] $end
$var wire 1 N add2_i [7] $end
$var wire 1 O add2_i [6] $end
$var wire 1 P add2_i [5] $end
$var wire 1 Q add2_i [4] $end
$var wire 1 R add2_i [3] $end
$var wire 1 S add2_i [2] $end
$var wire 1 T add2_i [1] $end
$var wire 1 U add2_i [0] $end
$var wire 1 # result_o [16] $end
$var wire 1 $ result_o [15] $end
$var wire 1 % result_o [14] $end
$var wire 1 & result_o [13] $end
$var wire 1 ' result_o [12] $end
$var wire 1 ( result_o [11] $end
$var wire 1 ) result_o [10] $end
$var wire 1 * result_o [9] $end
$var wire 1 + result_o [8] $end
$var wire 1 , result_o [7] $end
$var wire 1 - result_o [6] $end
$var wire 1 . result_o [5] $end
$var wire 1 / result_o [4] $end
$var wire 1 0 result_o [3] $end
$var wire 1 1 result_o [2] $end
$var wire 1 2 result_o [1] $end
$var wire 1 3 result_o [0] $end
$var wire 1 V sum_w [16] $end
$var wire 1 W sum_w [15] $end
$var wire 1 X sum_w [14] $end
$var wire 1 Y sum_w [13] $end
$var wire 1 Z sum_w [12] $end
$var wire 1 [ sum_w [11] $end
$var wire 1 \ sum_w [10] $end
$var wire 1 ] sum_w [9] $end
$var wire 1 ^ sum_w [8] $end
$var wire 1 _ sum_w [7] $end
$var wire 1 ` sum_w [6] $end
$var wire 1 a sum_w [5] $end
$var wire 1 b sum_w [4] $end
$var wire 1 c sum_w [3] $end
$var wire 1 d sum_w [2] $end
$var wire 1 e sum_w [1] $end
$var wire 1 f sum_w [0] $end
$var wire 1 g carry_w $end
$scope begin genblk1[3] $end
$var parameter 32 h i $end
$upscope $end
$scope begin genblk1[2] $end
$var parameter 32 i i $end
$upscope $end
$scope begin genblk1[1] $end
$var parameter 32 j i $end
$upscope $end
$scope begin genblk1[0] $end
$var parameter 32 k i $end
$upscope $end
$scope module rca $end
$var parameter 32 l width $end
$var wire 1 6 add1_i [11] $end
$var wire 1 7 add1_i [10] $end
$var wire 1 8 add1_i [9] $end
$var wire 1 9 add1_i [8] $end
$var wire 1 : add1_i [7] $end
$var wire 1 ; add1_i [6] $end
$var wire 1 < add1_i [5] $end
$var wire 1 = add1_i [4] $end
$var wire 1 > add1_i [3] $end
$var wire 1 ? add1_i [2] $end
$var wire 1 @ add1_i [1] $end
$var wire 1 A add1_i [0] $end
$var wire 1 F add2_i [11] $end
$var wire 1 G add2_i [10] $end
$var wire 1 H add2_i [9] $end
$var wire 1 I add2_i [8] $end
$var wire 1 J add2_i [7] $end
$var wire 1 K add2_i [6] $end
$var wire 1 L add2_i [5] $end
$var wire 1 M add2_i [4] $end
$var wire 1 N add2_i [3] $end
$var wire 1 O add2_i [2] $end
$var wire 1 P add2_i [1] $end
$var wire 1 Q add2_i [0] $end
$var wire 1 g carry_i $end
$var wire 1 V result_o [12] $end
$var wire 1 W result_o [11] $end
$var wire 1 X result_o [10] $end
$var wire 1 Y result_o [9] $end
$var wire 1 Z result_o [8] $end
$var wire 1 [ result_o [7] $end
$var wire 1 \ result_o [6] $end
$var wire 1 ] result_o [5] $end
$var wire 1 ^ result_o [4] $end
$var wire 1 _ result_o [3] $end
$var wire 1 ` result_o [2] $end
$var wire 1 a result_o [1] $end
$var wire 1 b result_o [0] $end
$var wire 1 m sum_w [11] $end
$var wire 1 n sum_w [10] $end
$var wire 1 o sum_w [9] $end
$var wire 1 p sum_w [8] $end
$var wire 1 q sum_w [7] $end
$var wire 1 r sum_w [6] $end
$var wire 1 s sum_w [5] $end
$var wire 1 t sum_w [4] $end
$var wire 1 u sum_w [3] $end
$var wire 1 v sum_w [2] $end
$var wire 1 w sum_w [1] $end
$var wire 1 x sum_w [0] $end
$var wire 1 y carry_w [12] $end
$var wire 1 z carry_w [11] $end
$var wire 1 { carry_w [10] $end
$var wire 1 | carry_w [9] $end
$var wire 1 } carry_w [8] $end
$var wire 1 ~ carry_w [7] $end
$var wire 1 !! carry_w [6] $end
$var wire 1 "! carry_w [5] $end
$var wire 1 #! carry_w [4] $end
$var wire 1 $! carry_w [3] $end
$var wire 1 %! carry_w [2] $end
$var wire 1 &! carry_w [1] $end
$var wire 1 '! carry_w [0] $end
$scope begin genblk1[11] $end
$var parameter 32 (! i $end
$upscope $end
$scope begin genblk1[10] $end
$var parameter 32 )! i $end
$upscope $end
$scope begin genblk1[9] $end
$var parameter 32 *! i $end
$upscope $end
$scope begin genblk1[8] $end
$var parameter 32 +! i $end
$upscope $end
$scope begin genblk1[7] $end
$var parameter 32 ,! i $end
$upscope $end
$scope begin genblk1[6] $end
$var parameter 32 -! i $end
$upscope $end
$scope begin genblk1[5] $end
$var parameter 32 .! i $end
$upscope $end
$scope begin genblk1[4] $end
$var parameter 32 /! i $end
$upscope $end
$scope begin genblk1[3] $end
$var parameter 32 0! i $end
$upscope $end
$scope begin genblk1[2] $end
$var parameter 32 1! i $end
$upscope $end
$scope begin genblk1[1] $end
$var parameter 32 2! i $end
$upscope $end
$scope begin genblk1[0] $end
$var parameter 32 3! i $end
$upscope $end
$scope unknown genblk1 $end
$upscope $end
$upscope $end
$scope unknown genblk1 $end
$upscope $end
$upscope $end
$upscope $end
$enddefinitions $end
#0
$dumpvars
b10000 4
b100 5
b1100 l
b0 3!
b1 2!
b10 1!
b11 0!
b100 /!
b101 .!
b110 -!
b111 ,!
b1000 +!
b1001 *!
b1010 )!
b1011 (!
b0 k
b1 j
b10 i
b11 h
b0 !
b0 "
03
02
01
00
0/
0.
0-
0,
0+
0*
0)
0(
0'
0&
0%
0$
0#
0f
0e
0d
0c
0b
0a
0`
0_
0^
0]
0\
0[
0Z
0Y
0X
0W
0V
0g
0x
0w
0v
0u
0t
0s
0r
0q
0p
0o
0n
0m
0'!
0&!
0%!
0$!
0#!
0"!
0!!
0~
0}
0|
0{
0z
0y
0U
0T
0S
0R
0Q
0P
0O
0N
0M
0L
0K
0J
0I
0H
0G
0F
0E
0D
0C
0B
0A
0@
0?
0>
0=
0<
0;
0:
09
08
07
06
$end
#10000
b10100110101111 !
b111101000011011 "
1U
1T
1R
1Q
1L
1J
1I
1H
1G
1E
1D
1C
1B
1@
1>
1=
1:
18
1{
1}
1t
1u
1w
1g
1d
1s
1x
1c
1e
1f
1'!
1|
1z
1m
1o
0x
1&!
0w
1%!
1v
13
12
11
10
1`
1_
1^
1]
1Y
1W
1-
1,
1+
1*
1&
1$
#20000
b1000100000000 !
b1000100010001 "
0T
0R
1M
0L
0J
0H
0G
0E
0D
0C
0B
0@
0>
0:
19
08
0{
1p
0u
1w
0%!
0c
0d
0e
0z
0}
0s
0t
1"!
0g
0'!
1s
0p
0m
0v
1x
0&!
0w
02
01
00
1b
0`
0_
0^
0W
1/
0-
0,
0+
0$
#30000
b1000000100010110 !
b1110011001110 "
0U
1T
1S
1R
0Q
1O
1N
0M
1K
1J
1D
1C
1A
09
16
1m
1p
0|
1q
1r
1t
0"!
1u
1v
1c
1d
1e
0f
0s
0o
03
12
11
10
1`
1_
1^
0]
1\
1[
1Z
0Y
1W
1-
1,
1+
0*
1)
1(
1'
0&
1$
#35000
b100010010000010 !
b11101111001101 "
1U
0T
1M
1L
0K
1H
0C
0A
1>
0=
1;
17
06
0m
1n
0u
1#!
0x
1o
1s
0t
1"!
1f
0s
1!!
0r
1~
0q
1}
0p
1|
0o
1{
0n
1z
1m
13
0b
0_
0^
0\
0[
0Z
0/
0,
0+
0)
0(
0'
#40000
b1000100101000011 !
b1111111111111111 "
1T
1Q
1P
1K
1G
1F
1E
1?
0>
1=
0;
1:
07
16
1q
1t
1u
0#!
0v
1$!
1y
1w
1x
0u
1#!
1b
1a
0`
1^
1[
1V
1/
1.
0-
1+
1(
1#
#50000
b1010101111001101 !
b0 "
0U
0T
0S
0R
0Q
0P
0O
0N
0M
0L
0K
0J
0I
0H
0G
0F
0D
1C
1B
1>
1<
18
0e
0m
1n
0z
1p
0|
0q
1r
0~
0t
1v
0$!
0w
0x
1u
0#!
1q
0}
1o
0{
1m
0y
0n
0p
1t
0"!
1s
0!!
0r
0b
0a
1`
1_
1]
1Y
0V
02
0/
0.
1-
1,
1*
1&
0#
#60000
b0 !
b1001000110100 "
1S
1Q
1P
1L
1I
0E
0C
0B
0?
0>
0=
0<
0:
08
06
0m
0o
0q
0t
0u
0v
0c
0f
1p
1w
1x
03
00
1b
1a
0`
0_
0^
0[
1Z
0Y
0W
1/
1.
0-
0,
0+
0(
1'
0&
0$
#70000
b1000100010001 !
b1110111010101010 "
1T
0S
1R
0Q
1N
1K
1J
0I
1H
1G
1F
1E
1A
1=
19
1t
1f
1m
1n
1o
1q
1r
1u
1c
0d
1e
13
12
01
10
1_
1^
1\
1[
1Y
1X
1W
1,
1+
1)
1(
1&
1%
1$
#80000
b101010101010101 !
b1010101010101010 "
0K
0G
1C
1?
1;
17
1v
1d
11
1`
1-
#90000
b1000000001010001 !
b1000000010000110 "
1S
0R
0P
0L
0J
0H
0C
0=
0;
09
07
16
0m
1y
0n
0p
0r
0t
0o
0q
0s
0w
0c
00
0a
0^
0]
0\
0[
0Z
0Y
0X
0W
1V
0.
0+
0*
0)
0(
0'
0&
0%
0$
1#
#95000
b1111101011011100 !
b11011100 "
0T
1R
1Q
1O
0F
0E
1C
1B
1>
1<
1:
19
18
17
1n
1o
1p
1q
1s
0u
1#!
1g
0f
1m
0y
0v
1$!
0x
1&!
1c
0e
1w
1u
1'!
1t
1x
03
02
10
1a
0`
1^
1]
1[
1Z
1Y
1X
1W
0V
1.
0-
1+
1*
1(
1'
1&
1%
1$
0#
#100000
b100000010010110 !
b10000001001000 "
0S
0Q
0N
1H
1D
0B
0?
0<
0:
09
08
06
0m
0p
0q
0s
1v
0$!
0g
1e
0x
0'!
0#!
0t
1x
0&!
0w
12
0a
1`
0^
0]
0[
0Z
0W
0.
1-
0+
0*
0(
0'
0$
#110000
b1000000100100 !
b1000000110010010 "
1T
0R
1Q
0O
1N
1M
0H
1F
0D
0A
1@
0>
19
07
0n
1p
1w
1m
0o
1t
0v
0c
00
1a
0`
1^
1Z
0Y
0X
1W
1.
0-
1+
1'
0&
0%
1$
#210000
b0 !
b1 "
1U
0T
0Q
0N
0M
0F
0C
0@
09
0p
0w
0d
0m
0t
0u
0x
0e
1f
13
02
01
0b
0a
0_
0^
0Z
0W
0/
0.
0,
0+
0'
0$
