multipliers16/traditional_multiplier16/msim/presynth/full_adder.v
`timescale 1ns / 1ps
//////////////////////////////////////////////////////////////////////////////////
// Company: 
// Engineer: 
// 
// Create Date:    15:11:39 06/09/2020 
// Design Name: 
// Module Name:    full_adder 
// Project Name: 
// Target Devices: 
// Tool versions: 
// Description: 
//
// Dependencies: 
//
// Revision: 
// Revision 0.01 - File Created
// Additional Comments: 
//
//////////////////////////////////////////////////////////////////////////////////
module full_adder(input1_i,input2_i,carry_i,sum_o,carry_o);
input input1_i, input2_i;
input carry_i;
output sum_o;
output carry_o;

assign sum_o = input1_i ^ input2_i ^ carry_i;
assign carry_o = (input1_i & input2_i) | (input1_i & carry_i) | (input2_i & carry_i);

endmodule

adders32/carry_lookahead_adder32/msim/presynth/carry_lookahead_adder32.v
`timescale 1ns / 1ps
//////////////////////////////////////////////////////////////////////////////////
// Company: 
// Engineer: 
// 
// Create Date:    14:19:28 06/09/2020 
// Design Name: 
// Module Name:    ripple_carry_adder 
// Project Name: 
// Target Devices: 
// Tool versions: 
// Description: 
//
// Dependencies: 
//
// Revision: 
// Revision 0.01 - File Created
// Additional Comments: 
//
//////////////////////////////////////////////////////////////////////////////////
module carry_lookahead_adder32(add1_i,add2_i,result_o);
parameter width =32;
input [width-1:0] add1_i;
input [width-1:0] add2_i;
output [width:0] result_o;

wire [width:0] carry_w;
wire [width-1:0] generate_w, propagate_w, sum_w;


genvar i;

generate
for(i=0; i<width; i = i+1)
begin 
full_adder fa(.input1_i(add1_i[i]), .input2_i(add2_i[i]), .carry_i(carry_w[i]), .sum_o(sum_w[i]), .carry_o());
end

endgenerate

genvar j;

generate
for(j=0; j<width; j = j+1)
begin
assign generate_w[j] = add1_i[j] & add2_i[j];
assign propagate_w[j] = add1_i[j] | add2_i[j];
assign carry_w[j+1] = generate_w[j]| (propagate_w[j] & carry_w[j]);
end

endgenerate

assign carry_w[0] = 1'b0;
assign result_o = {carry_w[width],sum_w};
endmodule

adders32/carry_lookahead_adder32/msim/presynth/carry_lookahead_adder32_tb.v
`timescale 1ns / 1ps
//////////////////////////////////////////////////////////////////////////////////
// Company: 
// Engineer: 
// 
// Create Date: 05/05/2020 01:15:36 AM
// Design Name: 
// Module Name: Test_Bench
// Project Name: 
// Target Devices: 
// Tool Versions: 
// Description: 
// 
// Dependencies: 
// 
// Revision:
// Revision 0.01 - File Created
// Additional Comments:
// 
//////////////////////////////////////////////////////////////////////////////////


module carry_lookahead_adder32_tb;
reg [31:0]add1_i;
reg [31:0]add2_i;
wire [32:0]result_o;


carry_lookahead_adder32 cla(add1_i,add2_i,result_o);

initial begin
   $dumpfile("carry_lookahead_adder32_sim.vcd");
   $dumpvars(2,carry_lookahead_adder32_tb);

   
   add1_i = 32'h0000_0000;
   add2_i = 32'h0000_0000;
   #10
   add1_i = 32'h29AF_2430;
   add2_i = 32'h7A1B_9ABC;
   #10
   add1_i = 32'h1100_3456;
   add2_i = 32'h1111_2323;
   #10
   add1_i = 32'h8116_0873;
   add2_i = 32'h1CCE_0178;
   #5
   add1_i = 32'h2020_2012;
   add2_i = 32'hDEAD_BEEF;
   #8
   add1_i = 32'h8943_DEAF;
   add2_i = 32'hDAAD_BAAD;
   #10
   add1_i = 32'hABCD_1234;
   add2_i = 32'h0000_0000;
   #10
   add1_i = 32'h0000_0000;
   add2_i = 32'h1234_5678;
   #10
   add1_i = 32'h1111_4477;
   add2_i = 32'hEEAA_0000;
  #10
   add1_i = 32'h5555_5555;
   add2_i = 32'hAAAA_AAAA;
  #10
   add1_i = 32'h8051_9860;
   add2_i = 32'h8086_BA3E;
  #5
  add1_i = 32'hFADC_0720;
  add2_i = 32'h00DC_0810;
 #8
  add1_i = 32'h4096_2048;
  add2_i = 32'h2048_4096;
 #10
  add1_i = 32'h1024_2048;
  add2_i = 32'h8192_4096;
  #100
  add1_i = 32'h0000_0001;
  add2_i = 32'hDEAF_BEEF;
  #100
  
   $finish;
    
   
 end

initial begin

$monitor($time , " add1_i= %h, add2_i = %h, result_o = %h ",add1_i, add2_i, result_o);
end
	
	
	
endmodule

adders32/carry_lookahead_adder32/msim/presynth/carry_lookahead_adder32_sim.vcd
$date
	Sun Aug 30 19:45:16 2020
$end
$version
	ModelSim Version 6.6d
$end
$timescale
	1ps
$end
$scope module carry_lookahead_adder32_tb $end
$var reg 32 ! add1_i [31:0] $end
$var reg 32 " add2_i [31:0] $end
$var wire 1 # result_o [32] $end
$var wire 1 $ result_o [31] $end
$var wire 1 % result_o [30] $end
$var wire 1 & result_o [29] $end
$var wire 1 ' result_o [28] $end
$var wire 1 ( result_o [27] $end
$var wire 1 ) result_o [26] $end
$var wire 1 * result_o [25] $end
$var wire 1 + result_o [24] $end
$var wire 1 , result_o [23] $end
$var wire 1 - result_o [22] $end
$var wire 1 . result_o [21] $end
$var wire 1 / result_o [20] $end
$var wire 1 0 result_o [19] $end
$var wire 1 1 result_o [18] $end
$var wire 1 2 result_o [17] $end
$var wire 1 3 result_o [16] $end
$var wire 1 4 result_o [15] $end
$var wire 1 5 result_o [14] $end
$var wire 1 6 result_o [13] $end
$var wire 1 7 result_o [12] $end
$var wire 1 8 result_o [11] $end
$var wire 1 9 result_o [10] $end
$var wire 1 : result_o [9] $end
$var wire 1 ; result_o [8] $end
$var wire 1 < result_o [7] $end
$var wire 1 = result_o [6] $end
$var wire 1 > result_o [5] $end
$var wire 1 ? result_o [4] $end
$var wire 1 @ result_o [3] $end
$var wire 1 A result_o [2] $end
$var wire 1 B result_o [1] $end
$var wire 1 C result_o [0] $end
$scope module cla $end
$var parameter 32 D width $end
$var wire 1 E add1_i [31] $end
$var wire 1 F add1_i [30] $end
$var wire 1 G add1_i [29] $end
$var wire 1 H add1_i [28] $end
$var wire 1 I add1_i [27] $end
$var wire 1 J add1_i [26] $end
$var wire 1 K add1_i [25] $end
$var wire 1 L add1_i [24] $end
$var wire 1 M add1_i [23] $end
$var wire 1 N add1_i [22] $end
$var wire 1 O add1_i [21] $end
$var wire 1 P add1_i [20] $end
$var wire 1 Q add1_i [19] $end
$var wire 1 R add1_i [18] $end
$var wire 1 S add1_i [17] $end
$var wire 1 T add1_i [16] $end
$var wire 1 U add1_i [15] $end
$var wire 1 V add1_i [14] $end
$var wire 1 W add1_i [13] $end
$var wire 1 X add1_i [12] $end
$var wire 1 Y add1_i [11] $end
$var wire 1 Z add1_i [10] $end
$var wire 1 [ add1_i [9] $end
$var wire 1 \ add1_i [8] $end
$var wire 1 ] add1_i [7] $end
$var wire 1 ^ add1_i [6] $end
$var wire 1 _ add1_i [5] $end
$var wire 1 ` add1_i [4] $end
$var wire 1 a add1_i [3] $end
$var wire 1 b add1_i [2] $end
$var wire 1 c add1_i [1] $end
$var wire 1 d add1_i [0] $end
$var wire 1 e add2_i [31] $end
$var wire 1 f add2_i [30] $end
$var wire 1 g add2_i [29] $end
$var wire 1 h add2_i [28] $end
$var wire 1 i add2_i [27] $end
$var wire 1 j add2_i [26] $end
$var wire 1 k add2_i [25] $end
$var wire 1 l add2_i [24] $end
$var wire 1 m add2_i [23] $end
$var wire 1 n add2_i [22] $end
$var wire 1 o add2_i [21] $end
$var wire 1 p add2_i [20] $end
$var wire 1 q add2_i [19] $end
$var wire 1 r add2_i [18] $end
$var wire 1 s add2_i [17] $end
$var wire 1 t add2_i [16] $end
$var wire 1 u add2_i [15] $end
$var wire 1 v add2_i [14] $end
$var wire 1 w add2_i [13] $end
$var wire 1 x add2_i [12] $end
$var wire 1 y add2_i [11] $end
$var wire 1 z add2_i [10] $end
$var wire 1 { add2_i [9] $end
$var wire 1 | add2_i [8] $end
$var wire 1 } add2_i [7] $end
$var wire 1 ~ add2_i [6] $end
$var wire 1 !! add2_i [5] $end
$var wire 1 "! add2_i [4] $end
$var wire 1 #! add2_i [3] $end
$var wire 1 $! add2_i [2] $end
$var wire 1 %! add2_i [1] $end
$var wire 1 &! add2_i [0] $end
$var wire 1 # result_o [32] $end
$var wire 1 $ result_o [31] $end
$var wire 1 % result_o [30] $end
$var wire 1 & result_o [29] $end
$var wire 1 ' result_o [28] $end
$var wire 1 ( result_o [27] $end
$var wire 1 ) result_o [26] $end
$var wire 1 * result_o [25] $end
$var wire 1 + result_o [24] $end
$var wire 1 , result_o [23] $end
$var wire 1 - result_o [22] $end
$var wire 1 . result_o [21] $end
$var wire 1 / result_o [20] $end
$var wire 1 0 result_o [19] $end
$var wire 1 1 result_o [18] $end
$var wire 1 2 result_o [17] $end
$var wire 1 3 result_o [16] $end
$var wire 1 4 result_o [15] $end
$var wire 1 5 result_o [14] $end
$var wire 1 6 result_o [13] $end
$var wire 1 7 result_o [12] $end
$var wire 1 8 result_o [11] $end
$var wire 1 9 result_o [10] $end
$var wire 1 : result_o [9] $end
$var wire 1 ; result_o [8] $end
$var wire 1 < result_o [7] $end
$var wire 1 = result_o [6] $end
$var wire 1 > result_o [5] $end
$var wire 1 ? result_o [4] $end
$var wire 1 @ result_o [3] $end
$var wire 1 A result_o [2] $end
$var wire 1 B result_o [1] $end
$var wire 1 C result_o [0] $end
$var wire 1 '! carry_w [32] $end
$var wire 1 (! carry_w [31] $end
$var wire 1 )! carry_w [30] $end
$var wire 1 *! carry_w [29] $end
$var wire 1 +! carry_w [28] $end
$var wire 1 ,! carry_w [27] $end
$var wire 1 -! carry_w [26] $end
$var wire 1 .! carry_w [25] $end
$var wire 1 /! carry_w [24] $end
$var wire 1 0! carry_w [23] $end
$var wire 1 1! carry_w [22] $end
$var wire 1 2! carry_w [21] $end
$var wire 1 3! carry_w [20] $end
$var wire 1 4! carry_w [19] $end
$var wire 1 5! carry_w [18] $end
$var wire 1 6! carry_w [17] $end
$var wire 1 7! carry_w [16] $end
$var wire 1 8! carry_w [15] $end
$var wire 1 9! carry_w [14] $end
$var wire 1 :! carry_w [13] $end
$var wire 1 ;! carry_w [12] $end
$var wire 1 <! carry_w [11] $end
$var wire 1 =! carry_w [10] $end
$var wire 1 >! carry_w [9] $end
$var wire 1 ?! carry_w [8] $end
$var wire 1 @! carry_w [7] $end
$var wire 1 A! carry_w [6] $end
$var wire 1 B! carry_w [5] $end
$var wire 1 C! carry_w [4] $end
$var wire 1 D! carry_w [3] $end
$var wire 1 E! carry_w [2] $end
$var wire 1 F! carry_w [1] $end
$var wire 1 G! carry_w [0] $end
$var wire 1 H! generate_w [31] $end
$var wire 1 I! generate_w [30] $end
$var wire 1 J! generate_w [29] $end
$var wire 1 K! generate_w [28] $end
$var wire 1 L! generate_w [27] $end
$var wire 1 M! generate_w [26] $end
$var wire 1 N! generate_w [25] $end
$var wire 1 O! generate_w [24] $end
$var wire 1 P! generate_w [23] $end
$var wire 1 Q! generate_w [22] $end
$var wire 1 R! generate_w [21] $end
$var wire 1 S! generate_w [20] $end
$var wire 1 T! generate_w [19] $end
$var wire 1 U! generate_w [18] $end
$var wire 1 V! generate_w [17] $end
$var wire 1 W! generate_w [16] $end
$var wire 1 X! generate_w [15] $end
$var wire 1 Y! generate_w [14] $end
$var wire 1 Z! generate_w [13] $end
$var wire 1 [! generate_w [12] $end
$var wire 1 \! generate_w [11] $end
$var wire 1 ]! generate_w [10] $end
$var wire 1 ^! generate_w [9] $end
$var wire 1 _! generate_w [8] $end
$var wire 1 `! generate_w [7] $end
$var wire 1 a! generate_w [6] $end
$var wire 1 b! generate_w [5] $end
$var wire 1 c! generate_w [4] $end
$var wire 1 d! generate_w [3] $end
$var wire 1 e! generate_w [2] $end
$var wire 1 f! generate_w [1] $end
$var wire 1 g! generate_w [0] $end
$var wire 1 h! propagate_w [31] $end
$var wire 1 i! propagate_w [30] $end
$var wire 1 j! propagate_w [29] $end
$var wire 1 k! propagate_w [28] $end
$var wire 1 l! propagate_w [27] $end
$var wire 1 m! propagate_w [26] $end
$var wire 1 n! propagate_w [25] $end
$var wire 1 o! propagate_w [24] $end
$var wire 1 p! propagate_w [23] $end
$var wire 1 q! propagate_w [22] $end
$var wire 1 r! propagate_w [21] $end
$var wire 1 s! propagate_w [20] $end
$var wire 1 t! propagate_w [19] $end
$var wire 1 u! propagate_w [18] $end
$var wire 1 v! propagate_w [17] $end
$var wire 1 w! propagate_w [16] $end
$var wire 1 x! propagate_w [15] $end
$var wire 1 y! propagate_w [14] $end
$var wire 1 z! propagate_w [13] $end
$var wire 1 {! propagate_w [12] $end
$var wire 1 |! propagate_w [11] $end
$var wire 1 }! propagate_w [10] $end
$var wire 1 ~! propagate_w [9] $end
$var wire 1 !" propagate_w [8] $end
$var wire 1 "" propagate_w [7] $end
$var wire 1 #" propagate_w [6] $end
$var wire 1 $" propagate_w [5] $end
$var wire 1 %" propagate_w [4] $end
$var wire 1 &" propagate_w [3] $end
$var wire 1 '" propagate_w [2] $end
$var wire 1 (" propagate_w [1] $end
$var wire 1 )" propagate_w [0] $end
$var wire 1 *" sum_w [31] $end
$var wire 1 +" sum_w [30] $end
$var wire 1 ," sum_w [29] $end
$var wire 1 -" sum_w [28] $end
$var wire 1 ." sum_w [27] $end
$var wire 1 /" sum_w [26] $end
$var wire 1 0" sum_w [25] $end
$var wire 1 1" sum_w [24] $end
$var wire 1 2" sum_w [23] $end
$var wire 1 3" sum_w [22] $end
$var wire 1 4" sum_w [21] $end
$var wire 1 5" sum_w [20] $end
$var wire 1 6" sum_w [19] $end
$var wire 1 7" sum_w [18] $end
$var wire 1 8" sum_w [17] $end
$var wire 1 9" sum_w [16] $end
$var wire 1 :" sum_w [15] $end
$var wire 1 ;" sum_w [14] $end
$var wire 1 <" sum_w [13] $end
$var wire 1 =" sum_w [12] $end
$var wire 1 >" sum_w [11] $end
$var wire 1 ?" sum_w [10] $end
$var wire 1 @" sum_w [9] $end
$var wire 1 A" sum_w [8] $end
$var wire 1 B" sum_w [7] $end
$var wire 1 C" sum_w [6] $end
$var wire 1 D" sum_w [5] $end
$var wire 1 E" sum_w [4] $end
$var wire 1 F" sum_w [3] $end
$var wire 1 G" sum_w [2] $end
$var wire 1 H" sum_w [1] $end
$var wire 1 I" sum_w [0] $end
$scope begin genblk2[31] $end
$var parameter 32 J" j $end
$upscope $end
$scope begin genblk2[30] $end
$var parameter 32 K" j $end
$upscope $end
$scope begin genblk2[29] $end
$var parameter 32 L" j $end
$upscope $end
$scope begin genblk2[28] $end
$var parameter 32 M" j $end
$upscope $end
$scope begin genblk2[27] $end
$var parameter 32 N" j $end
$upscope $end
$scope begin genblk2[26] $end
$var parameter 32 O" j $end
$upscope $end
$scope begin genblk2[25] $end
$var parameter 32 P" j $end
$upscope $end
$scope begin genblk2[24] $end
$var parameter 32 Q" j $end
$upscope $end
$scope begin genblk2[23] $end
$var parameter 32 R" j $end
$upscope $end
$scope begin genblk2[22] $end
$var parameter 32 S" j $end
$upscope $end
$scope begin genblk2[21] $end
$var parameter 32 T" j $end
$upscope $end
$scope begin genblk2[20] $end
$var parameter 32 U" j $end
$upscope $end
$scope begin genblk2[19] $end
$var parameter 32 V" j $end
$upscope $end
$scope begin genblk2[18] $end
$var parameter 32 W" j $end
$upscope $end
$scope begin genblk2[17] $end
$var parameter 32 X" j $end
$upscope $end
$scope begin genblk2[16] $end
$var parameter 32 Y" j $end
$upscope $end
$scope begin genblk2[15] $end
$var parameter 32 Z" j $end
$upscope $end
$scope begin genblk2[14] $end
$var parameter 32 [" j $end
$upscope $end
$scope begin genblk2[13] $end
$var parameter 32 \" j $end
$upscope $end
$scope begin genblk2[12] $end
$var parameter 32 ]" j $end
$upscope $end
$scope begin genblk2[11] $end
$var parameter 32 ^" j $end
$upscope $end
$scope begin genblk2[10] $end
$var parameter 32 _" j $end
$upscope $end
$scope begin genblk2[9] $end
$var parameter 32 `" j $end
$upscope $end
$scope begin genblk2[8] $end
$var parameter 32 a" j $end
$upscope $end
$scope begin genblk2[7] $end
$var parameter 32 b" j $end
$upscope $end
$scope begin genblk2[6] $end
$var parameter 32 c" j $end
$upscope $end
$scope begin genblk2[5] $end
$var parameter 32 d" j $end
$upscope $end
$scope begin genblk2[4] $end
$var parameter 32 e" j $end
$upscope $end
$scope begin genblk2[3] $end
$var parameter 32 f" j $end
$upscope $end
$scope begin genblk2[2] $end
$var parameter 32 g" j $end
$upscope $end
$scope begin genblk2[1] $end
$var parameter 32 h" j $end
$upscope $end
$scope begin genblk2[0] $end
$var parameter 32 i" j $end
$upscope $end
$scope begin genblk1[31] $end
$var parameter 32 j" i $end
$upscope $end
$scope begin genblk1[30] $end
$var parameter 32 k" i $end
$upscope $end
$scope begin genblk1[29] $end
$var parameter 32 l" i $end
$upscope $end
$scope begin genblk1[28] $end
$var parameter 32 m" i $end
$upscope $end
$scope begin genblk1[27] $end
$var parameter 32 n" i $end
$upscope $end
$scope begin genblk1[26] $end
$var parameter 32 o" i $end
$upscope $end
$scope begin genblk1[25] $end
$var parameter 32 p" i $end
$upscope $end
$scope begin genblk1[24] $end
$var parameter 32 q" i $end
$upscope $end
$scope begin genblk1[23] $end
$var parameter 32 r" i $end
$upscope $end
$scope begin genblk1[22] $end
$var parameter 32 s" i $end
$upscope $end
$scope begin genblk1[21] $end
$var parameter 32 t" i $end
$upscope $end
$scope begin genblk1[20] $end
$var parameter 32 u" i $end
$upscope $end
$scope begin genblk1[19] $end
$var parameter 32 v" i $end
$upscope $end
$scope begin genblk1[18] $end
$var parameter 32 w" i $end
$upscope $end
$scope begin genblk1[17] $end
$var parameter 32 x" i $end
$upscope $end
$scope begin genblk1[16] $end
$var parameter 32 y" i $end
$upscope $end
$scope begin genblk1[15] $end
$var parameter 32 z" i $end
$upscope $end
$scope begin genblk1[14] $end
$var parameter 32 {" i $end
$upscope $end
$scope begin genblk1[13] $end
$var parameter 32 |" i $end
$upscope $end
$scope begin genblk1[12] $end
$var parameter 32 }" i $end
$upscope $end
$scope begin genblk1[11] $end
$var parameter 32 ~" i $end
$upscope $end
$scope begin genblk1[10] $end
$var parameter 32 !# i $end
$upscope $end
$scope begin genblk1[9] $end
$var parameter 32 "# i $end
$upscope $end
$scope begin genblk1[8] $end
$var parameter 32 ## i $end
$upscope $end
$scope begin genblk1[7] $end
$var parameter 32 $# i $end
$upscope $end
$scope begin genblk1[6] $end
$var parameter 32 %# i $end
$upscope $end
$scope begin genblk1[5] $end
$var parameter 32 &# i $end
$upscope $end
$scope begin genblk1[4] $end
$var parameter 32 '# i $end
$upscope $end
$scope begin genblk1[3] $end
$var parameter 32 (# i $end
$upscope $end
$scope begin genblk1[2] $end
$var parameter 32 )# i $end
$upscope $end
$scope begin genblk1[1] $end
$var parameter 32 *# i $end
$upscope $end
$scope begin genblk1[0] $end
$var parameter 32 +# i $end
$upscope $end
$scope unknown genblk1 $end
$upscope $end
$scope unknown genblk2 $end
$upscope $end
$upscope $end
$upscope $end
$enddefinitions $end
#0
$dumpvars
b100000 D
b0 +#
b1 *#
b10 )#
b11 (#
b100 '#
b101 &#
b110 %#
b111 $#
b1000 ##
b1001 "#
b1010 !#
b1011 ~"
b1100 }"
b1101 |"
b1110 {"
b1111 z"
b10000 y"
b10001 x"
b10010 w"
b10011 v"
b10100 u"
b10101 t"
b10110 s"
b10111 r"
b11000 q"
b11001 p"
b11010 o"
b11011 n"
b11100 m"
b11101 l"
b11110 k"
b11111 j"
b0 i"
b1 h"
b10 g"
b11 f"
b100 e"
b101 d"
b110 c"
b111 b"
b1000 a"
b1001 `"
b1010 _"
b1011 ^"
b1100 ]"
b1101 \"
b1110 ["
b1111 Z"
b10000 Y"
b10001 X"
b10010 W"
b10011 V"
b10100 U"
b10101 T"
b10110 S"
b10111 R"
b11000 Q"
b11001 P"
b11010 O"
b11011 N"
b11100 M"
b11101 L"
b11110 K"
b11111 J"
b0 !
b0 "
0C
0B
0A
0@
0?
0>
0=
0<
0;
0:
09
08
07
06
05
04
03
02
01
00
0/
0.
0-
0,
0+
0*
0)
0(
0'
0&
0%
0$
0#
0G!
0F!
0E!
0D!
0C!
0B!
0A!
0@!
0?!
0>!
0=!
0<!
0;!
0:!
09!
08!
07!
06!
05!
04!
03!
02!
01!
00!
0/!
0.!
0-!
0,!
0+!
0*!
0)!
0(!
0'!
0g!
0f!
0e!
0d!
0c!
0b!
0a!
0`!
0_!
0^!
0]!
0\!
0[!
0Z!
0Y!
0X!
0W!
0V!
0U!
0T!
0S!
0R!
0Q!
0P!
0O!
0N!
0M!
0L!
0K!
0J!
0I!
0H!
0)"
0("
0'"
0&"
0%"
0$"
0#"
0""
0!"
0~!
0}!
0|!
0{!
0z!
0y!
0x!
0w!
0v!
0u!
0t!
0s!
0r!
0q!
0p!
0o!
0n!
0m!
0l!
0k!
0j!
0i!
0h!
0I"
0H"
0G"
0F"
0E"
0D"
0C"
0B"
0A"
0@"
0?"
0>"
0="
0<"
0;"
0:"
09"
08"
07"
06"
05"
04"
03"
02"
01"
00"
0/"
0."
0-"
0,"
0+"
0*"
0&!
0%!
0$!
0#!
0"!
0!!
0~
0}
0|
0{
0z
0y
0x
0w
0v
0u
0t
0s
0r
0q
0p
0o
0n
0m
0l
0k
0j
0i
0h
0g
0f
0e
0d
0c
0b
0a
0`
0_
0^
0]
0\
0[
0Z
0Y
0X
0W
0V
0U
0T
0S
0R
0Q
0P
0O
0N
0M
0L
0K
0J
0I
0H
0G
0F
0E
$end
#10000
b101001101011110010010000110000 !
b1111010000110111001101010111100 "
1$!
1#!
1"!
1!!
1}
1{
1y
1x
1u
1t
1s
1q
1p
1k
1i
1h
1g
1f
1`
1_
1Z
1W
1T
1S
1R
1Q
1O
1M
1L
1I
1G
1J!
1L!
11"
1o!
12"
1p!
14"
1r!
1T!
17"
1u!
1V!
1W!
1<"
1z!
1?"
1}!
1b!
1c!
1+"
1i!
1j!
1-"
1k!
1l!
10"
1n!
15"
1s!
1t!
1v!
1w!
1:"
1x!
1="
1{!
1>"
1|!
1@"
1~!
1B"
1""
1$"
1%"
1F"
1&"
1G"
1'"
1B!
1A!
16!
15!
13!
1+!
1)!
0+"
1(!
0-"
1*!
05"
12!
07"
14!
18"
1C"
1D"
16"
04"
11!
1,"
1*"
13"
1A
1@
1>
1=
1<
1:
19
18
17
16
14
12
10
1-
1,
1+
1*
1&
1$
#20000
b10001000000000011010001010110 !
b10001000100010010001100100011 "
1&!
1%!
0$!
0#!
0"!
0}
1|
0y
0x
1w
0u
0s
0q
1l
0k
0i
0g
0f
1c
1b
0_
1^
1X
0T
0S
0R
0Q
0O
0M
0I
1H
0G
0j!
1-"
1K!
0l!
02"
0p!
14"
0r!
0t!
17"
0u!
0v!
19"
0W!
0C"
1#"
0D"
0b!
1f!
1+"
0i!
0J!
0L!
00"
0n!
01"
1O!
0T!
0V!
0:"
0x!
0<"
1Z!
0>"
0|!
1A"
1!"
0B"
0""
1E"
0c!
0F"
0&"
1("
1I"
1)"
0B!
19!
05!
03!
1.!
0+!
0)!
0(!
1E!
1@!
06!
04!
01!
03"
06"
08"
1B"
0G"
1D!
0*"
0+"
0-"
10"
15"
02!
07"
1;"
1D"
0A!
1C"
0@!
04"
1F"
0B"
1C
0A
1?
0<
1;
08
06
15
04
13
02
00
1/
0-
0,
0+
0$
#30000
b10000001000101100000100001110011 !
b11100110011100000000101111000 "
0&!
0%!
1#!
1"!
1~
0{
0w
0t
1s
1r
1q
0p
1n
1m
0l
1j
1i
1d
0b
1_
0Z
1Y
0X
0W
1S
1R
1P
0H
1E
1*"
1h!
1-"
0K!
1U!
1V!
0z!
0="
0{!
1>"
1|!
0?"
0}!
0D"
1b!
1G"
0'"
1."
1l!
1/"
1m!
11"
0O!
12"
1p!
13"
1q!
16"
1t!
1u!
1v!
09"
0w!
0Z!
0@"
0~!
0C"
1a!
0E"
1c!
0F"
1&"
1H"
0f!
0E!
1C!
1B!
1@!
09!
0.!
0D!
1A!
15!
14!
0*!
0,"
06"
13!
17"
1C"
1F"
0C!
00"
0;"
1B"
1D"
0G"
05"
12!
14"
1B
0?
1<
0:
09
18
07
05
03
11
0/
1.
1-
1,
1+
0*
1)
1(
1'
0&
1$
#35000
b100000001000000010000000010010 !
b11011110101011011011111011101111 "
1&!
1%!
1$!
0"!
1}
0|
1{
1z
1y
1x
1w
1u
1t
0s
1o
0n
1k
1f
1e
0d
0_
0^
0Y
1W
0S
0R
0P
1O
0L
1G
0E
1,"
1j!
01"
0o!
1R!
15"
0s!
07"
0U!
0v!
1Z!
0C"
0a!
0D"
0b!
1+"
1i!
10"
1n!
03"
0q!
1r!
0V!
19"
1w!
1:"
1x!
1z!
1="
1{!
1?"
1}!
1@"
1~!
0A"
0!"
0B"
1""
1E"
0c!
1G"
1'"
0H"
1f!
1E!
0B!
1?!
05!
19!
02!
11!
13"
04"
1;"
17"
04!
1A"
1D"
0A!
0G"
1D!
0F"
1C!
1C"
0@!
16"
03!
05"
1B"
0?!
0E"
1B!
0D"
1A!
0A"
0C"
1@!
0B"
1?!
1A"
0B
0@
0>
0=
0<
1:
19
17
15
14
13
10
0.
0+
1*
1&
1%
#43000
b10001001010000111101111010101111 !
b11011010101011011011101010101101 "
0%!
0~
0z
0j
1d
1b
1a
0`
1_
1]
1[
1Z
1Y
1X
0W
1V
1U
1T
1S
0O
1N
1L
1I
0G
1E
0*"
1H!
0,"
0j!
0."
1L!
11"
1o!
03"
1q!
14"
0R!
18"
1v!
09"
1W!
0:"
1X!
0;"
1y!
1<"
0Z!
0="
1[!
0>"
1\!
0@"
1^!
1B"
1`!
1D"
1b!
1E"
0%"
1F"
1d!
1G"
1e!
0I"
1g!
0/"
0m!
1C"
0#"
1H"
0f!
0E!
0@!
1F!
0B!
1=!
1;!
1:!
18!
17!
16!
01!
1+!
1'!
0-"
1*!
13"
08"
15!
19"
1:"
0<"
1="
0?"
1<!
0D"
0H"
1E!
0B"
1>"
07"
14!
1,"
06"
13!
15"
0C
1A
1@
1?
1=
0:
09
05
01
00
1/
1.
1+
0)
0(
0'
0$
1#
#53000
b10101011110011010001001000110100 !
b0 "
0&!
0$!
0#!
0!!
0}
0{
0y
0x
0w
0u
0t
0r
0q
0o
0m
0k
0i
0h
0f
0e
0d
0c
0a
1`
0]
0Z
0Y
0V
0U
0S
1R
1Q
1M
1K
1G
0,"
1j!
18"
0v!
0x!
1;"
0y!
0|!
1?"
0}!
0""
0E"
1%"
0&"
1H"
0("
0)"
1*"
0H!
0+"
0i!
1-"
0k!
1."
0L!
04"
0r!
09"
0W!
0X!
1<"
0z!
0="
0[!
0\!
1@"
0^!
0`!
1D"
0b!
0d!
0G"
0e!
0g!
0F!
0C!
0A!
0?!
0=!
0;!
09!
07!
0+!
0*!
0'!
0E!
0<!
08!
05!
17"
04!
0:"
0>"
1G"
0D!
1,"
0-"
19"
06!
0;"
1="
0:!
0?"
0A"
0C"
1E"
0H"
0<"
08"
0F"
16"
03!
05"
0@
1>
0=
0;
1:
08
04
11
10
0/
0.
1(
0%
1$
0#
#63000
b0 !
b10010001101000101011001111000 "
1#!
1"!
1!!
1~
1{
1z
1x
1v
1r
1p
1o
1k
1h
0b
0`
0_
0[
0X
0T
0R
0Q
0N
0M
0L
0K
0I
0G
0E
0*"
0h!
0,"
0j!
0."
0l!
01"
0o!
02"
0p!
03"
0q!
06"
0t!
09"
0w!
0G"
0'"
1-"
1k!
14"
1r!
15"
1s!
1;"
1y!
1?"
1}!
1C"
1#"
1F"
1&"
0A
1@
1=
19
15
03
00
1/
1.
0-
0,
0+
0(
1'
0&
0$
#73000
b10001000100010100010001110111 !
b11101110101010100000000000000000 "
0#!
0"!
0!!
0~
0{
0z
0x
0v
1s
0r
1q
0p
1m
1j
1i
0h
1g
1f
1e
1d
1c
1b
1`
1_
1^
1Z
1V
1T
1P
1L
1H
11"
1o!
19"
1w!
1G"
1'"
1H"
1("
1I"
1)"
1*"
1h!
1+"
1i!
1,"
1j!
1."
1l!
1/"
1m!
12"
1p!
16"
1t!
07"
0u!
18"
1v!
0="
0{!
0@"
0~!
0F"
0&"
1C
1B
1A
0@
0:
07
13
12
01
10
1,
1+
1)
1(
1&
1%
1$
#83000
b1010101010101010101010101010101 !
b10101010101010101010101010101010 "
1%!
1#!
1!!
1}
1{
1y
1w
1u
0j
0f
0c
0_
1\
1X
1R
1N
1J
1F
13"
1q!
17"
1u!
1="
1{!
1A"
1!"
1:"
1x!
1<"
1z!
1>"
1|!
1@"
1~!
1B"
1""
1F"
1&"
1@
1<
1;
1:
18
17
16
14
11
1-
#93000
b10000000010100011001100001100000 !
b10000000100001101011101000111110 "
1$!
1"!
0}
1x
1r
0q
0o
0k
0i
0g
0d
0b
0`
1_
0\
0Z
1Y
0V
1U
0R
0L
0J
0H
0F
1E
0*"
1H!
0+"
0i!
0-"
0k!
0/"
0m!
01"
0o!
0:"
1X!
0;"
0y!
0>"
1\!
0?"
0}!
0A"
0!"
0D"
1b!
0I"
0)"
0,"
0j!
0."
0l!
00"
0n!
04"
0r!
06"
0t!
0="
1[!
0B"
0""
1:!
1A!
1;!
17!
1'!
09"
16!
1="
0C"
1@!
0<"
19!
1;"
1B"
08"
15!
07"
14!
16"
0C
0>
0=
0;
09
08
06
04
03
02
01
0.
0+
0*
0)
0(
0'
0&
0%
0$
1#
