multipliers16/traditional_multiplier16/msim/presynth/full_adder.v
`timescale 1ns / 1ps
//////////////////////////////////////////////////////////////////////////////////
// Company: 
// Engineer: 
// 
// Create Date:    15:11:39 06/09/2020 
// Design Name: 
// Module Name:    full_adder 
// Project Name: 
// Target Devices: 
// Tool versions: 
// Description: 
//
// Dependencies: 
//
// Revision: 
// Revision 0.01 - File Created
// Additional Comments: 
//
//////////////////////////////////////////////////////////////////////////////////
module full_adder(input1_i,input2_i,carry_i,sum_o,carry_o);
input input1_i, input2_i;
input carry_i;
output sum_o;
output carry_o;

assign sum_o = input1_i ^ input2_i ^ carry_i;
assign carry_o = (input1_i & input2_i) | (input1_i & carry_i) | (input2_i & carry_i);

endmodule

adders/lower_part_or_carry_lookahead_adder16/msim/presynth/carry_lookahead_adder.v
`timescale 1ns / 1ps
//////////////////////////////////////////////////////////////////////////////////
// Company: 
// Engineer: 
// 
// Create Date:    14:19:28 06/09/2020 
// Design Name: 
// Module Name:    carry_lookahead_adder 
// Project Name: 
// Target Devices: 
// Tool versions: 
// Description: 
//
// Dependencies: 
//
// Revision: 
// Revision 0.01 - File Created
// Additional Comments: 
//
//////////////////////////////////////////////////////////////////////////////////
module carry_lookahead_adder(add1_i,add2_i, carry_i, result_o);
parameter width =12;
input [width-1:0] add1_i;
input [width-1:0] add2_i;
input carry_i;
output [width:0] result_o;

wire [width:0] carry_w;
wire [width-1:0] generate_w, propagate_w, sum_w;


genvar i;

generate
for(i=0; i<width; i = i+1)
begin 
full_adder fa(.input1_i(add1_i[i]), .input2_i(add2_i[i]), .carry_i(carry_w[i]), .sum_o(sum_w[i]), .carry_o());
end

endgenerate

genvar j;

generate
for(j=0; j<width; j = j+1)
begin
assign generate_w[j] = add1_i[j] & add2_i[j];
assign propagate_w[j] = add1_i[j] | add2_i[j];
assign carry_w[j+1] = generate_w[j]| (propagate_w[j] & carry_w[j]);
end

endgenerate

assign carry_w[0] = carry_i;
assign result_o = {carry_w[width],sum_w};
endmodule

adders16/lower_part_or_carry_lookahead_adder16/snps/lower_part_or_carry_lookahead_adder16.v
module lower_part_or_carry_lookahead_adder16(add1_i, add2_i, result_o);
  parameter width = 16;
  parameter lower_width = 4;
  
  input [width-1:0] add1_i;
  input [width-1:0] add2_i;
  output [width:0] result_o;
  
  
  wire [width:0] sum_w;
  wire  carry_w;
  
  assign carry_w = add1_i[lower_width-1] & add2_i[lower_width-1];
  
  
  genvar i;
  
  generate
  for(i=0; i<lower_width; i=i+1)
  begin
  assign sum_w[i] = add1_i[i] | add2_i[i];
  end
  endgenerate
        
        
  carry_lookahead_adder cla(.add1_i(add1_i[width-1:lower_width]), .add2_i(add2_i[width-1:lower_width]), .carry_i(carry_w), .result_o(sum_w[width:lower_width]));
  
  assign result_o = sum_w;
  
endmodule

adders16/lower_part_or_carry_lookahead_adder16/msim/presynth/lower_part_or_carry_lookahead_adder16_tb.v
`timescale 1ns / 1ps
//////////////////////////////////////////////////////////////////////////////////
// Company: 
// Engineer: 
// 
// Create Date: 05/05/2020 01:15:36 AM
// Design Name: 
// Module Name: Test_Bench
// Project Name: 
// Target Devices: 
// Tool Versions: 
// Description: 
// 
// Dependencies: 
// 
// Revision:
// Revision 0.01 - File Created
// Additional Comments:
// 
//////////////////////////////////////////////////////////////////////////////////


module lower_part_or_carry_lookahead_adder16_tb;
reg [15:0]add1_i;
reg [15:0]add2_i;
wire [16:0]result_o;


lower_part_or_carry_lookahead_adder16 loacla
(add1_i,add2_i,result_o);

initial begin
   $dumpfile("lower_part_or_carry_lookahead_adder16_sim.vcd");
   $dumpvars(3,lower_part_or_carry_lookahead_adder16_tb);

   
   add1_i = 16'h0000;
   add2_i = 16'h0000;
   #10
   add1_i = 16'h29AF;
   add2_i = 16'h7A1B;
   #10
   add1_i = 16'h1100;
   add2_i = 16'h1111;
   #10
   add1_i = 16'h8116;
   add2_i = 16'h1CCE;
   #5
   add1_i = 16'h4482;
   add2_i = 16'h3BCD;
   #5
   add1_i = 16'h8943;
   add2_i = 16'hFFFF;
   #10
   add1_i = 16'hABCD;
   add2_i = 16'h0000;
   #10
   add1_i = 16'h0000;
   add2_i = 16'h1234;
   #10
   add1_i = 16'h1111;
   add2_i = 16'hEEAA;
  #10
   add1_i = 16'h5555;
   add2_i = 16'hAAAA;
  #10
   add1_i = 16'h8051;
   add2_i = 16'h8086;
  #5
  add1_i = 16'hFADC;
  add2_i = 16'h00DC;
 #5
  add1_i = 16'h4096;
  add2_i = 16'h2048;
 #10
  add1_i = 16'h1024;
  add2_i = 16'h8192;
  #100
   add1_i = 16'h0000;
   add2_i = 16'h0001;
  #100
  
   $finish;
    
   
 end

initial begin

$monitor($time , " add1_i= %h, add2_i = %h, result_o = %h ",add1_i, add2_i, result_o);
end
	
	
	
endmodule

adders/lower_part_or_carry_lookahead_adder16/msim/presynth/lower_part_or_carry_lookahead_adder16_sim.vcd
$date
	Wed Aug  5 23:02:43 2020
$end
$version
	ModelSim Version 6.6d
$end
$timescale
	1ps
$end
$scope module lower_part_or_carry_lookahead_adder16_tb $end
$var reg 16 ! add1_i [15:0] $end
$var reg 16 " add2_i [15:0] $end
$var wire 1 # result_o [16] $end
$var wire 1 $ result_o [15] $end
$var wire 1 % result_o [14] $end
$var wire 1 & result_o [13] $end
$var wire 1 ' result_o [12] $end
$var wire 1 ( result_o [11] $end
$var wire 1 ) result_o [10] $end
$var wire 1 * result_o [9] $end
$var wire 1 + result_o [8] $end
$var wire 1 , result_o [7] $end
$var wire 1 - result_o [6] $end
$var wire 1 . result_o [5] $end
$var wire 1 / result_o [4] $end
$var wire 1 0 result_o [3] $end
$var wire 1 1 result_o [2] $end
$var wire 1 2 result_o [1] $end
$var wire 1 3 result_o [0] $end
$scope module loacla $end
$var parameter 32 4 width $end
$var parameter 32 5 lower_width $end
$var wire 1 6 add1_i [15] $end
$var wire 1 7 add1_i [14] $end
$var wire 1 8 add1_i [13] $end
$var wire 1 9 add1_i [12] $end
$var wire 1 : add1_i [11] $end
$var wire 1 ; add1_i [10] $end
$var wire 1 < add1_i [9] $end
$var wire 1 = add1_i [8] $end
$var wire 1 > add1_i [7] $end
$var wire 1 ? add1_i [6] $end
$var wire 1 @ add1_i [5] $end
$var wire 1 A add1_i [4] $end
$var wire 1 B add1_i [3] $end
$var wire 1 C add1_i [2] $end
$var wire 1 D add1_i [1] $end
$var wire 1 E add1_i [0] $end
$var wire 1 F add2_i [15] $end
$var wire 1 G add2_i [14] $end
$var wire 1 H add2_i [13] $end
$var wire 1 I add2_i [12] $end
$var wire 1 J add2_i [11] $end
$var wire 1 K add2_i [10] $end
$var wire 1 L add2_i [9] $end
$var wire 1 M add2_i [8] $end
$var wire 1 N add2_i [7] $end
$var wire 1 O add2_i [6] $end
$var wire 1 P add2_i [5] $end
$var wire 1 Q add2_i [4] $end
$var wire 1 R add2_i [3] $end
$var wire 1 S add2_i [2] $end
$var wire 1 T add2_i [1] $end
$var wire 1 U add2_i [0] $end
$var wire 1 # result_o [16] $end
$var wire 1 $ result_o [15] $end
$var wire 1 % result_o [14] $end
$var wire 1 & result_o [13] $end
$var wire 1 ' result_o [12] $end
$var wire 1 ( result_o [11] $end
$var wire 1 ) result_o [10] $end
$var wire 1 * result_o [9] $end
$var wire 1 + result_o [8] $end
$var wire 1 , result_o [7] $end
$var wire 1 - result_o [6] $end
$var wire 1 . result_o [5] $end
$var wire 1 / result_o [4] $end
$var wire 1 0 result_o [3] $end
$var wire 1 1 result_o [2] $end
$var wire 1 2 result_o [1] $end
$var wire 1 3 result_o [0] $end
$var wire 1 V sum_w [16] $end
$var wire 1 W sum_w [15] $end
$var wire 1 X sum_w [14] $end
$var wire 1 Y sum_w [13] $end
$var wire 1 Z sum_w [12] $end
$var wire 1 [ sum_w [11] $end
$var wire 1 \ sum_w [10] $end
$var wire 1 ] sum_w [9] $end
$var wire 1 ^ sum_w [8] $end
$var wire 1 _ sum_w [7] $end
$var wire 1 ` sum_w [6] $end
$var wire 1 a sum_w [5] $end
$var wire 1 b sum_w [4] $end
$var wire 1 c sum_w [3] $end
$var wire 1 d sum_w [2] $end
$var wire 1 e sum_w [1] $end
$var wire 1 f sum_w [0] $end
$var wire 1 g carry_w $end
$scope begin genblk1[3] $end
$var parameter 32 h i $end
$upscope $end
$scope begin genblk1[2] $end
$var parameter 32 i i $end
$upscope $end
$scope begin genblk1[1] $end
$var parameter 32 j i $end
$upscope $end
$scope begin genblk1[0] $end
$var parameter 32 k i $end
$upscope $end
$scope module cla $end
$var parameter 32 l width $end
$var wire 1 6 add1_i [11] $end
$var wire 1 7 add1_i [10] $end
$var wire 1 8 add1_i [9] $end
$var wire 1 9 add1_i [8] $end
$var wire 1 : add1_i [7] $end
$var wire 1 ; add1_i [6] $end
$var wire 1 < add1_i [5] $end
$var wire 1 = add1_i [4] $end
$var wire 1 > add1_i [3] $end
$var wire 1 ? add1_i [2] $end
$var wire 1 @ add1_i [1] $end
$var wire 1 A add1_i [0] $end
$var wire 1 F add2_i [11] $end
$var wire 1 G add2_i [10] $end
$var wire 1 H add2_i [9] $end
$var wire 1 I add2_i [8] $end
$var wire 1 J add2_i [7] $end
$var wire 1 K add2_i [6] $end
$var wire 1 L add2_i [5] $end
$var wire 1 M add2_i [4] $end
$var wire 1 N add2_i [3] $end
$var wire 1 O add2_i [2] $end
$var wire 1 P add2_i [1] $end
$var wire 1 Q add2_i [0] $end
$var wire 1 g carry_i $end
$var wire 1 V result_o [12] $end
$var wire 1 W result_o [11] $end
$var wire 1 X result_o [10] $end
$var wire 1 Y result_o [9] $end
$var wire 1 Z result_o [8] $end
$var wire 1 [ result_o [7] $end
$var wire 1 \ result_o [6] $end
$var wire 1 ] result_o [5] $end
$var wire 1 ^ result_o [4] $end
$var wire 1 _ result_o [3] $end
$var wire 1 ` result_o [2] $end
$var wire 1 a result_o [1] $end
$var wire 1 b result_o [0] $end
$var wire 1 m carry_w [12] $end
$var wire 1 n carry_w [11] $end
$var wire 1 o carry_w [10] $end
$var wire 1 p carry_w [9] $end
$var wire 1 q carry_w [8] $end
$var wire 1 r carry_w [7] $end
$var wire 1 s carry_w [6] $end
$var wire 1 t carry_w [5] $end
$var wire 1 u carry_w [4] $end
$var wire 1 v carry_w [3] $end
$var wire 1 w carry_w [2] $end
$var wire 1 x carry_w [1] $end
$var wire 1 y carry_w [0] $end
$var wire 1 z generate_w [11] $end
$var wire 1 { generate_w [10] $end
$var wire 1 | generate_w [9] $end
$var wire 1 } generate_w [8] $end
$var wire 1 ~ generate_w [7] $end
$var wire 1 !! generate_w [6] $end
$var wire 1 "! generate_w [5] $end
$var wire 1 #! generate_w [4] $end
$var wire 1 $! generate_w [3] $end
$var wire 1 %! generate_w [2] $end
$var wire 1 &! generate_w [1] $end
$var wire 1 '! generate_w [0] $end
$var wire 1 (! propagate_w [11] $end
$var wire 1 )! propagate_w [10] $end
$var wire 1 *! propagate_w [9] $end
$var wire 1 +! propagate_w [8] $end
$var wire 1 ,! propagate_w [7] $end
$var wire 1 -! propagate_w [6] $end
$var wire 1 .! propagate_w [5] $end
$var wire 1 /! propagate_w [4] $end
$var wire 1 0! propagate_w [3] $end
$var wire 1 1! propagate_w [2] $end
$var wire 1 2! propagate_w [1] $end
$var wire 1 3! propagate_w [0] $end
$var wire 1 4! sum_w [11] $end
$var wire 1 5! sum_w [10] $end
$var wire 1 6! sum_w [9] $end
$var wire 1 7! sum_w [8] $end
$var wire 1 8! sum_w [7] $end
$var wire 1 9! sum_w [6] $end
$var wire 1 :! sum_w [5] $end
$var wire 1 ;! sum_w [4] $end
$var wire 1 <! sum_w [3] $end
$var wire 1 =! sum_w [2] $end
$var wire 1 >! sum_w [1] $end
$var wire 1 ?! sum_w [0] $end
$scope begin genblk2[11] $end
$var parameter 32 @! j $end
$upscope $end
$scope begin genblk2[10] $end
$var parameter 32 A! j $end
$upscope $end
$scope begin genblk2[9] $end
$var parameter 32 B! j $end
$upscope $end
$scope begin genblk2[8] $end
$var parameter 32 C! j $end
$upscope $end
$scope begin genblk2[7] $end
$var parameter 32 D! j $end
$upscope $end
$scope begin genblk2[6] $end
$var parameter 32 E! j $end
$upscope $end
$scope begin genblk2[5] $end
$var parameter 32 F! j $end
$upscope $end
$scope begin genblk2[4] $end
$var parameter 32 G! j $end
$upscope $end
$scope begin genblk2[3] $end
$var parameter 32 H! j $end
$upscope $end
$scope begin genblk2[2] $end
$var parameter 32 I! j $end
$upscope $end
$scope begin genblk2[1] $end
$var parameter 32 J! j $end
$upscope $end
$scope begin genblk2[0] $end
$var parameter 32 K! j $end
$upscope $end
$scope begin genblk1[11] $end
$var parameter 32 L! i $end
$upscope $end
$scope begin genblk1[10] $end
$var parameter 32 M! i $end
$upscope $end
$scope begin genblk1[9] $end
$var parameter 32 N! i $end
$upscope $end
$scope begin genblk1[8] $end
$var parameter 32 O! i $end
$upscope $end
$scope begin genblk1[7] $end
$var parameter 32 P! i $end
$upscope $end
$scope begin genblk1[6] $end
$var parameter 32 Q! i $end
$upscope $end
$scope begin genblk1[5] $end
$var parameter 32 R! i $end
$upscope $end
$scope begin genblk1[4] $end
$var parameter 32 S! i $end
$upscope $end
$scope begin genblk1[3] $end
$var parameter 32 T! i $end
$upscope $end
$scope begin genblk1[2] $end
$var parameter 32 U! i $end
$upscope $end
$scope begin genblk1[1] $end
$var parameter 32 V! i $end
$upscope $end
$scope begin genblk1[0] $end
$var parameter 32 W! i $end
$upscope $end
$scope unknown genblk1 $end
$upscope $end
$scope unknown genblk2 $end
$upscope $end
$upscope $end
$scope unknown genblk1 $end
$upscope $end
$upscope $end
$upscope $end
$enddefinitions $end
#0
$dumpvars
b10000 4
b100 5
b1100 l
b0 W!
b1 V!
b10 U!
b11 T!
b100 S!
b101 R!
b110 Q!
b111 P!
b1000 O!
b1001 N!
b1010 M!
b1011 L!
b0 K!
b1 J!
b10 I!
b11 H!
b100 G!
b101 F!
b110 E!
b111 D!
b1000 C!
b1001 B!
b1010 A!
b1011 @!
b0 k
b1 j
b10 i
b11 h
b0 !
b0 "
03
02
01
00
0/
0.
0-
0,
0+
0*
0)
0(
0'
0&
0%
0$
0#
0f
0e
0d
0c
0b
0a
0`
0_
0^
0]
0\
0[
0Z
0Y
0X
0W
0V
0g
0y
0x
0w
0v
0u
0t
0s
0r
0q
0p
0o
0n
0m
0'!
0&!
0%!
0$!
0#!
0"!
0!!
0~
0}
0|
0{
0z
03!
02!
01!
00!
0/!
0.!
0-!
0,!
0+!
0*!
0)!
0(!
0?!
0>!
0=!
0<!
0;!
0:!
09!
08!
07!
06!
05!
04!
0U
0T
0S
0R
0Q
0P
0O
0N
0M
0L
0K
0J
0I
0H
0G
0F
0E
0D
0C
0B
0A
0@
0?
0>
0=
0<
0;
0:
09
08
07
06
$end
#10000
b10100110101111 !
b111101000011011 "
1U
1T
1R
1Q
1L
1J
1I
1H
1G
1E
1D
1C
1B
1@
1>
1=
1:
18
1|
1~
1;!
1/!
1<!
10!
1>!
12!
1g
1d
15!
1)!
1*!
17!
1+!
1,!
1:!
1.!
1?!
13!
1c
1e
1f
1y
1q
1o
05!
1n
07!
1p
0?!
1x
0>!
1w
16!
14!
1=!
13
12
11
10
1`
1_
1^
1]
1Y
1W
1-
1,
1+
1*
1&
1$
#20000
b1000100000000 !
b1000100010001 "
0T
0R
1M
0L
0J
0H
0G
0E
0D
0C
0B
0@
0>
0:
19
08
0*!
17!
1}
0,!
0<!
00!
1>!
02!
0c
0d
0e
15!
0)!
0|
0~
0:!
0.!
0;!
1#!
0g
0y
1t
0q
0o
0n
0w
0=!
04!
05!
07!
1:!
1?!
0x
0>!
02
01
00
1b
0`
0_
0^
0W
1/
0-
0,
0+
0$
#30000
b1000000100010110 !
b1110011001110 "
0U
1T
1S
1R
0Q
1O
1N
0M
1K
1J
1D
1C
1A
09
16
14!
1(!
17!
0}
18!
1,!
19!
1-!
1;!
0#!
1<!
10!
1=!
11!
1c
1d
1e
0f
0t
0p
06!
0:!
03
12
11
10
1`
1_
1^
0]
1\
1[
1Z
0Y
1W
1-
1,
1+
0*
1)
1(
1'
0&
1$
#35000
b100010010000010 !
b11101111001101 "
1U
0T
1M
1L
0K
1H
0C
0A
1>
0=
1;
17
06
04!
0(!
15!
1)!
0<!
1$!
0?!
03!
16!
1*!
1:!
1.!
1f
1u
0;!
1t
0:!
1s
09!
1r
08!
1q
07!
1p
06!
1o
05!
1n
14!
13
0b
0_
0^
0\
0[
0Z
0/
0,
0+
0)
0(
0'
#40000
b1000100101000011 !
b1111111111111111 "
1T
1Q
1P
1K
1G
1F
1E
1?
0>
1=
0;
1:
07
16
1z
18!
1~
1;!
1#!
1<!
0$!
0=!
1%!
1(!
1>!
12!
1?!
13!
1v
1m
0<!
1b
1a
0`
1^
1[
1V
1/
1.
0-
1+
1(
1#
#50000
b1010101111001101 !
b0 "
0U
0T
0S
0R
0Q
0P
0O
0N
0M
0L
0K
0J
0I
0H
0G
0F
0D
1C
1B
1>
1<
18
0e
04!
0z
15!
0)!
17!
0+!
08!
0~
19!
0-!
0;!
0#!
1=!
0%!
0>!
02!
0?!
03!
0v
0r
0p
0n
14!
0m
16!
0o
18!
0q
1<!
0u
1;!
0t
07!
05!
1:!
0s
09!
0b
0a
1`
1_
1]
1Y
0V
02
0/
0.
1-
1,
1*
1&
0#
#60000
b0 !
b1001000110100 "
1S
1Q
1P
1L
1I
0E
0C
0B
0?
0>
0=
0<
0:
08
06
04!
0(!
06!
0*!
08!
0,!
0;!
0/!
0<!
00!
0=!
01!
0c
0f
17!
1+!
1>!
12!
1?!
13!
03
00
1b
1a
0`
0_
0^
0[
1Z
0Y
0W
1/
1.
0-
0,
0+
0(
1'
0&
0$
#70000
b1000100010001 !
b1110111010101010 "
1T
0S
1R
0Q
1N
1K
1J
0I
1H
1G
1F
1E
1A
1=
19
1;!
1/!
1f
14!
1(!
15!
1)!
16!
1*!
18!
1,!
19!
1-!
1<!
10!
1c
0d
1e
13
12
01
10
1_
1^
1\
1[
1Y
1X
1W
1,
1+
1)
1(
1&
1%
1$
#80000
b101010101010101 !
b1010101010101010 "
0K
0G
1C
1?
1;
17
1=!
11!
1d
11
1`
1-
#90000
b1000000001010001 !
b1000000010000110 "
1S
0R
0P
0L
0J
0H
0C
0=
0;
09
07
16
04!
1z
05!
0)!
07!
0+!
09!
0-!
0;!
0/!
06!
0*!
08!
0,!
0:!
0.!
0>!
02!
0c
1m
00
0a
0^
0]
0\
0[
0Z
0Y
0X
0W
1V
0.
0+
0*
0)
0(
0'
0&
0%
0$
1#
#95000
b1111101011011100 !
b11011100 "
0T
1R
1Q
1O
0F
0E
1C
1B
1>
1<
1:
19
18
17
15!
1)!
16!
1*!
17!
1+!
18!
1,!
1:!
1.!
0<!
1$!
1g
0f
14!
0z
0=!
1%!
0?!
1'!
1c
0e
1x
1v
0m
1y
1u
1;!
1?!
1<!
1>!
03
02
10
1a
0`
1^
1]
1[
1Z
1Y
1X
1W
0V
1.
0-
1+
1*
1(
1'
1&
1%
1$
0#
#100000
b100000010010110 !
b10000001001000 "
0S
0Q
0N
1H
1D
0B
0?
0<
0:
09
08
06
04!
0(!
07!
0+!
08!
0,!
0:!
0.!
1=!
0%!
0g
1e
0<!
0$!
0?!
0'!
0y
0v
1<!
0u
1?!
0x
0>!
0;!
12
0a
1`
0^
0]
0[
0Z
0W
0.
1-
0+
0*
0(
0'
0$
#110000
b1000000100100 !
b1000000110010010 "
1T
0R
1Q
0O
1N
1M
0H
1F
0D
0A
1@
0>
19
07
05!
0)!
17!
1+!
1>!
12!
14!
1(!
06!
0*!
1;!
1/!
0=!
01!
0c
00
1a
0`
1^
1Z
0Y
0X
1W
1.
0-
1+
1'
0&
0%
1$
#210000
b0 !
b1 "
1U
0T
0Q
0N
0M
0F
0C
0@
09
07!
0+!
0>!
02!
0d
04!
0(!
0;!
0/!
0<!
00!
0?!
03!
0e
1f
13
02
01
0b
0a
0_
0^
0Z
0W
0/
0.
0,
0+
0'
0$
